RTL/MEM/imem.v
//Verilog code for Instruction Memory

module imem(

input wire [31:0] ip_instr_addr_from_proc,
output reg [31:0] op_instr_from_imem,
output reg op_instr_valid
);

//Memory to hold the instructions

reg [31:0] mem[31:0];

//Reading instruction is harmless and it doesn't need any control signal
always @(*) begin: imem_block
	op_instr_from_imem= mem[ip_instr_addr_from_proc [31:2]];
	op_instr_valid =1'b1;
end

endmodule

RTL/CORES/Reg_Imm_Mem_Beq_v2/pc.v
//Verilog Code for Program Counter

module pc(

input wire clk,
input wire rst,
output reg [31:0] op_instr_addr
);

//reg rst_tracker;
reg [31:0] pc;
reg [31:0] next_pc;

always @(posedge clk) begin: PC_Block
	//rst_tracker <= rst;
	
	if (rst) begin
		pc <= 0;
	end
	else begin
		pc <= next_pc;
	end
end

always @(*) begin
	op_instr_addr = pc;	
	next_pc = pc + 32'h4;
end

endmodule

RTL/CORES/Reg_Imm_Mem/register_file.v
// Feb 10, 2023
// Verilog Code for Register File

module regfile( 

input wire [4:0] reg_src1,
input wire [4:0] reg_src2,
input wire [4:0] reg_dest,
input wire [31:0] write_back,
input wire clk,
input wire rst,
input wire write_en,
output reg [31:0] read_data1,
output reg [31:0] read_data2
);

//32 Registers of each 32 bit
reg [31:0] mem[31:0];

//Reading from register file is harmless so no need of the control signal

always @(*) begin
	read_data1=mem[reg_src1];
	read_data2=mem[reg_src2];
end

always @(posedge clk ) begin: register_file_block
	if (write_en) begin
		mem[reg_dest] <= write_back;
	end
	
	//0th Register always holds value 0's
	mem[0] <= 'b0;
end


//always @(posedge clk or posedge rst) begin: register_file_block
//	if (rst) begin
//		mem <= 'b0;
//	end
//	else begin
//	 	if (write_en) begin
//			mem[reg_dst] <= write_back;
//		end
//	end
//	//0th Register always holds value 0's
//	mem[0] <= 'b0;
//end

endmodule

RTL/CORES/Reg_Imm_Mem_Beq_v2/mux_32.v
//Verilog Module for 32 bit Mux Logic


module mux_32(
input wire [31:0] inp0,
input wire [31:0] inp1,
input wire sel,
output reg [31:0] out
);

always @(*) begin
	if (sel) 
		out = inp1;
	else
		out = inp0;
end
endmodule

BRANCH_CASES/Reg_Imm_Mem_Beq/alu.v
//Verilog Code for ALU

module alu(

input wire [31:0] read_data1,
input wire [31:0] read_data2,
input wire [2:0] funct3,
input wire [6:0] funct7,
output reg [31:0] result
);

always @(*) begin: ALU_Block
	case (funct3)
		3'b000 :
		begin	
			if (funct7 != 7'b0100000)
				result = read_data1 + read_data2;   //ADD
			else
				result = read_data1 - read_data2;   //SUB 
		end
		3'b001 : result = read_data1 << read_data2;  //Shift Logical Left
		3'b010 : 				     //Set Less Than		
			if (read_data1 < read_data2) begin
				result = 1;
			end
			else begin 
				result = 0;
			end
		3'b011 :				     //S.L.T.Unsigned
 			if (read_data1 < read_data2) begin
				result = 1;
			end
			else begin 
				result = 0;
			end
		3'b100 : result = (read_data1 ^ read_data2); //XOR
		3'b101 :
		begin
			if (funct7 != 7'b0100000) 	
				result = read_data1 >> read_data2;  //Shift Right Logical
			else
				result = read_data1 >>> read_data2; //Shift Right Arithmetic
		end	
		3'b110 : result = read_data1 | read_data2;  //OR
		3'b111 : result = read_data1 & read_data2;  //AND
		default: result = 'b0;
	endcase
	
end
endmodule

BRANCH_CASES/Reg_Imm_Mem_Beq/decoder.v
//Verilog code for the Decoder- to generate control signals.

module decoder(

input wire [31:0] ip_instr_from_imem,
input wire ip_instr_valid,
output reg reg_write,
output reg [2:0] funct3,
output reg [6:0] funct7,
output reg alu_src_from_imem,
output reg mem_read,
output reg mem_write,
output reg mem_to_reg,
output reg [31:0] imem_sign_ext,
output reg beq,
output reg bne,
output reg blt,
output reg bge
);

always @(*) begin:decoder_block
	if (ip_instr_valid) begin
		case (ip_instr_from_imem[6:0]) 
			7'b0110011: //R-type Instruction 
			begin
				reg_write=1'b1;
			        alu_src_from_imem = 1'b0;	
				//3bit-Opcode
				funct3=ip_instr_from_imem[14:12];
				//7bit-Functionality
				funct7=ip_instr_from_imem[31:25];
				mem_read = 1'b0;
				mem_write = 1'b0;
				mem_to_reg = 1'b0;
			 	imem_sign_ext = 32'b0;

				beq = 1'b0;
				bne = 1'b0;
				blt = 1'b0;
				bge = 1'b0;
			end

			7'b0010011: //Immediate Type Instruction
			begin
				alu_src_from_imem = 1'b1;
				reg_write = 1'b1;
				//3bit-Opcode
				funct3 = ip_instr_from_imem[14:12];	
				//7bit-Functionality
				funct7 = ip_instr_from_imem[31:25];
				mem_read = 1'b0;
				mem_write = 1'b0;
				mem_to_reg = 1'b0;
				if ((funct3 != 3'b001) && (funct3 != 3'b101))
					imem_sign_ext = {{20{ip_instr_from_imem[31]}}, ip_instr_from_imem[31:20]};
				else
					imem_sign_ext = {{20{1'b0}}, {7{1'b0}}, ip_instr_from_imem[24:20]};

				beq = 1'b0;
				bne = 1'b0;
				blt = 1'b0;
				bge = 1'b0;
			end

			7'b0000011: //Load Word
			begin
				alu_src_from_imem = 1'b1;
				reg_write = 1'b1;
				//funct3 = ip_instr_from_imem[14:12];
				funct3 = 3'b000;
				funct7 = 7'b0;
				mem_read = 1'b1;
				mem_write = 1'b0;
				mem_to_reg = 1'b1;
				imem_sign_ext = {{20{ip_instr_from_imem[31]}}, ip_instr_from_imem[31:20]};

				beq = 1'b0;
				bne = 1'b0;
				blt = 1'b0;
				bge = 1'b0;
			end

			7'b0100011: //Store Word
			begin
				alu_src_from_imem = 1'b1;
				reg_write = 1'b0;
				//funct3 = ip_instr_from_imem[14:12];
				funct3 = 3'b000;
				funct7 = 7'b0;
				mem_read = 1'b0;
				mem_write = 1'b1;
				mem_to_reg = 1'bx;
				imem_sign_ext = {{20{ip_instr_from_imem[31]}}, ip_instr_from_imem[31:25], ip_instr_from_imem[11:7]};

				beq = 1'b0;
				bne = 1'b0;
				blt = 1'b0;
				bge = 1'b0;
			end

			7'b1100011: //Controlled Branches
			begin
				alu_src_from_imem = 1'b0;
				reg_write = 1'b0;
				funct3 = 3'b000;
				funct7 = 7'b0100000;
				mem_read = 1'b0;
				mem_write = 1'b0;
				mem_to_reg = 1'bx;
				imem_sign_ext = {{20{ip_instr_from_imem[31]}}, ip_instr_from_imem[7], ip_instr_from_imem[30:25], ip_instr_from_imem[11:8], 1'b0};
				
				case (ip_instr_from_imem[14:12])
					3'b000:
					begin
						beq = 1'b1;
						bne = 1'b0;
						blt = 1'b0;
						bge = 1'b0;
					end

					3'b001:
					begin
						beq = 1'b0;
						bne = 1'b1;
						blt = 1'b0;
						bge = 1'b0;
					end

					3'b100:
					begin
						beq = 1'b0;
						bne = 1'b0;
						blt = 1'b1;
						bge = 1'b0;
					end
					
					3'b101:
					begin
						beq = 1'b0;
						bne = 1'b0;
						blt = 1'b0;
						bge = 1'b1;
					end
				endcase						
			end
		endcase
	end

end
endmodule

RTL/CORES/Reg_Imm/processor_v1.v
//Verilog Code for single cycle processor- Only R-Type Instruction

module processor_v1(

//General inputs
input wire clk,
input wire rst,

//Inputs and Outputs from imem 
input wire [31:0] ip_instr_from_imem,
input wire ip_instr_valid,
output reg [31:0] op_instr_addr_from_proc

);

wire [31:0] read_data1;
wire [31:0] read_data2;
wire [31:0] op_data_from_proc;

//wires to and from Decoder Module
wire alu_src_from_imem;
wire [2:0] funct3;
wire [6:0] funct7;
wire op_data_wr;

//wire op_instr_addr_from_proc;
wire [31:0] ip_instr_addr_from_pc;

// intermediate signals wrt immediate instr
reg [31:0] imem_sign_ext;
wire [31:0] read_data_from_mux;

always @(*) begin
	op_instr_addr_from_proc = ip_instr_addr_from_pc;
	//Sign Extending the 12bit immediate field
	if (alu_src_from_imem) begin
		if ((funct3 != 3'b001) && (funct3 != 3'b101))
			imem_sign_ext = {{20{ip_instr_from_imem[31]}}, ip_instr_from_imem[31:20]};
		else
			imem_sign_ext = {{20{1'b0}}, {7{1'b0}}, ip_instr_from_imem[24:20]};
	end
	else
		imem_sign_ext = 32'b0;

end

decoder dec_0 (
.ip_instr_from_imem(ip_instr_from_imem),  
.funct3(funct3), //control signal for ALU
.funct7(funct7), //control signal for ALU
.ip_instr_valid(ip_instr_valid), //instr is valid or not
.reg_write(op_data_wr), //register wrtie instr or not
.alu_src_from_imem(alu_src_from_imem) //reading either from reg_file or immediate data
);

alu alu_0 (
.read_data1(read_data1), //read data1 
.read_data2(read_data_from_mux), //read data either from reg_file or immediate
.funct3(funct3), 
.funct7(funct7), 
.result(op_data_from_proc) //final result from ALU
);

mux_32 mux_32_0 (
.inp0(read_data2),
.inp1(imem_sign_ext),
.sel(alu_src_from_imem),
.out(read_data_from_mux)
);

regfile regfile_0 (
.reg_src1(ip_instr_from_imem[19:15]), //reg_source 1
.reg_src2(ip_instr_from_imem[24:20]), //reg_source 2
.reg_dest(ip_instr_from_imem[11:7]),  //reg_dest
.write_back(op_data_from_proc), //data to be written
.clk(clk), 
.rst(rst), 
.write_en(op_data_wr), //to write into reg_file if its a reg_write instr
.read_data1(read_data1), //data from reg_source1
.read_data2(read_data2) //data from reg_source2
);

pc pc_0 (
.clk(clk), 
.rst(rst), 
.op_instr_addr(ip_instr_addr_from_pc)
);


endmodule

RTL/SoC.v
//Top Module which instantiate Memory Modules and Processor 

module SoC (
	//General Inputs
	input wire clk,
	input wire rst
);

wire [31:0] instr_addr_from_proc; 


wire [31:0] instr_from_imem;
wire instr_valid_from_imem;

//Instantiation of Processor and IMEM

processor_v1 processor_v1_0 (
	.clk(clk), 
	.rst(rst), 
	.ip_instr_from_imem(instr_from_imem), 
	.ip_instr_valid(instr_valid_from_imem), 
	.op_instr_addr_from_proc(instr_addr_from_proc)
);

imem imem_0 (
.ip_instr_addr_from_proc(instr_addr_from_proc), 
.op_instr_from_imem(instr_from_imem), 
.op_instr_valid(instr_valid_from_imem)
);

endmodule

TESTS/002_IType_tests/tb.v
//Verilog Code for testing the Processor

//TestBench- Inputs and Outputs which you are giving and viewing respectively.
//Also to facilitate instantiation between two or more instants of module
//(Primarly taking and giving values between instanted modules)

`timescale 1ns/1ps

module tb;

reg clk;
reg rst;

//Clock
always #5 clk = ~clk;

//To count number of clocks
integer clock;

//To open the reg file and to dump data into it
integer reg_file_contents;
integer i;

initial begin

	//Dumping values into VCD using system_task for plotting signals
	$dumpfile("wave.vcd");

	//Dumping all the top level signal of the test bench- scope:0 
	$dumpvars(0, tb);
	
	//Storing the values from imem file to imem memory
	$readmemh("imem.fill", SoC_0.imem_0.mem);
	$readmemh("rf.fill", SoC_0.processor_v1_0.regfile_0.mem);
	
	//Resetting the Values
	clk <= 0;
	rst <= 1;
	clock <= 0;

	//After 5 negedge make reset 0
	@(negedge clk);

	repeat(5) begin 
		@(negedge clk);
	end
	
	rst <= 0;

	//Once the reset is 0, the program will run and by fetching the
	//instruction all 32 bit 0 indicated the end of the program.
	wait(SoC_0.instr_from_imem == 32'b0);
	$display("The program completed in the %d clock cycles", clock);

	////Draining pipeline
	//repeat(5) @(negedge clk);

	//Dump all the content in the registers into the file with dump
	//extenstion
	reg_file_contents=$fopen("rf_values.dump");

	for(i=0; i<32 ; i=i+1) begin
		$fdisplay(reg_file_contents,"Register %d : %h", i, SoC_0.processor_v1_0.regfile_0.mem[i]);
	end
	$fclose(reg_file_contents);
	$finish;
end

always @(posedge clk) begin
	if (rst) begin
		clock <= 0;
	end
	else begin
		clock <= clock + 1;
	end
end

//To avoid infinte loops
initial begin
	#1000
	$display("Test timeout, there should be infinite loop!!! Please check");
	$finish;
end

//Instantiation of SoC

SoC SoC_0 (
	.clk(clk),
	.rst(rst)
);

endmodule

TESTS/002_IType_tests/wave.vcd
$date
	Mon Mar 13 21:42:45 2023
$end
$version
	Icarus Verilog
$end
$timescale
	1ps
$end
$scope module tb $end
$var reg 1 ! clk $end
$var reg 1 " rst $end
$var integer 32 # clock [31:0] $end
$var integer 32 $ i [31:0] $end
$var integer 32 % reg_file_contents [31:0] $end
$scope module SoC_0 $end
$var wire 1 ! clk $end
$var wire 1 " rst $end
$var wire 1 & instr_valid_from_imem $end
$var wire 32 ' instr_from_imem [31:0] $end
$var wire 32 ( instr_addr_from_proc [31:0] $end
$scope module imem_0 $end
$var wire 32 ) ip_instr_addr_from_proc [31:0] $end
$var reg 32 * op_instr_from_imem [31:0] $end
$var reg 1 & op_instr_valid $end
$scope begin imem_block $end
$upscope $end
$upscope $end
$scope module processor_v1_0 $end
$var wire 1 ! clk $end
$var wire 32 + ip_instr_from_imem [31:0] $end
$var wire 1 & ip_instr_valid $end
$var wire 1 " rst $end
$var wire 32 , read_data_from_mux [31:0] $end
$var wire 32 - read_data2 [31:0] $end
$var wire 32 . read_data1 [31:0] $end
$var wire 1 / op_data_wr $end
$var wire 32 0 op_data_from_proc [31:0] $end
$var wire 32 1 ip_instr_addr_from_pc [31:0] $end
$var wire 7 2 funct7 [6:0] $end
$var wire 3 3 funct3 [2:0] $end
$var wire 1 4 alu_src_from_imem $end
$var reg 32 5 imem_sign_ext [31:0] $end
$var reg 32 6 op_instr_addr_from_proc [31:0] $end
$scope module alu_0 $end
$var wire 32 7 read_data2 [31:0] $end
$var wire 32 8 read_data1 [31:0] $end
$var wire 7 9 funct7 [6:0] $end
$var wire 3 : funct3 [2:0] $end
$var reg 32 ; result [31:0] $end
$scope begin ALU_Block $end
$upscope $end
$upscope $end
$scope module dec_0 $end
$var wire 32 < ip_instr_from_imem [31:0] $end
$var wire 1 & ip_instr_valid $end
$var reg 1 4 alu_src_from_imem $end
$var reg 3 = funct3 [2:0] $end
$var reg 7 > funct7 [6:0] $end
$var reg 1 / reg_write $end
$scope begin decoder_block $end
$upscope $end
$upscope $end
$scope module mux_32_0 $end
$var wire 32 ? inp1 [31:0] $end
$var wire 1 4 sel $end
$var wire 32 @ inp0 [31:0] $end
$var reg 32 A out [31:0] $end
$upscope $end
$scope module pc_0 $end
$var wire 1 ! clk $end
$var wire 1 " rst $end
$var reg 32 B next_pc [31:0] $end
$var reg 32 C op_instr_addr [31:0] $end
$var reg 32 D pc [31:0] $end
$scope begin PC_Block $end
$upscope $end
$upscope $end
$scope module regfile_0 $end
$var wire 1 ! clk $end
$var wire 5 E reg_dest [4:0] $end
$var wire 5 F reg_src1 [4:0] $end
$var wire 5 G reg_src2 [4:0] $end
$var wire 1 " rst $end
$var wire 32 H write_back [31:0] $end
$var wire 1 / write_en $end
$var reg 32 I read_data1 [31:0] $end
$var reg 32 J read_data2 [31:0] $end
$scope begin register_file_block $end
$upscope $end
$upscope $end
$upscope $end
$upscope $end
$upscope $end
$enddefinitions $end
#0
$dumpvars
bx J
bx I
bx H
bx G
bx F
bx E
bx D
bx C
bx B
bx A
bx @
bx ?
bx >
bx =
bx <
bx ;
bx :
bx 9
bx 8
bx 7
bx 6
bx 5
x4
bx 3
bx 2
bx 1
bx 0
x/
bx .
bx -
bx ,
bx +
bx *
bx )
bx (
bx '
1&
bx %
bx $
b0 #
1"
0!
$end
#5000
b110110 0
b110110 ;
b110110 H
b101100 ,
b101100 7
b101100 A
b101100 -
b101100 @
b101100 J
b1010 .
b1010 8
b1010 I
b100 F
b1000 G
b11 E
b0 2
b0 9
b0 >
b0 3
b0 :
b0 =
04
1/
b100000100000000110110011 '
b100000100000000110110011 *
b100000100000000110110011 +
b100000100000000110110011 <
b0 5
b0 ?
b0 (
b0 )
b0 6
b100 B
b0 1
b0 C
b0 D
1!
#10000
0!
#15000
1!
#20000
0!
#25000
1!
#30000
0!
#35000
1!
#40000
0!
#45000
1!
#50000
0"
0!
#55000
b10 ,
b10 7
b10 A
b11 0
b11 ;
b11 H
b10 -
b10 @
b10 J
b1 .
b1 8
b1 I
b1 F
b10 G
b10 E
b1000001000000100110011 '
b1000001000000100110011 *
b1000001000000100110011 +
b1000001000000100110011 <
b100 (
b100 )
b100 6
b1000 B
b100 1
b100 C
b100 D
b1 #
1!
#60000
0!
#65000
b11 .
b11 8
b11 I
b10 F
b11 G
b1000 E
b1100010000010000110011 '
b1100010000010000110011 *
b1100010000010000110011 +
b1100010000010000110011 <
b111001 0
b111001 ;
b111001 H
b1000 (
b1000 )
b1000 6
b110110 ,
b110110 7
b110110 A
b1100 B
b1000 1
b1000 C
b110110 -
b110110 @
b110110 J
b1000 D
b10 #
1!
#70000
0!
#75000
b110 ,
b110 7
b110 A
b110 -
b110 @
b110 J
b1111000000000001 .
b1111000000000001 8
b1111000000000001 I
b1111000000000001000000 0
b1111000000000001000000 ;
b1111000000000001000000 H
b1011 F
b1100 G
b1010 E
b1 3
b1 :
b1 =
b110001011001010100110011 '
b110001011001010100110011 *
b110001011001010100110011 +
b110001011001010100110011 <
b1100 (
b1100 )
b1100 6
b10000 B
b1100 1
b1100 C
b1100 D
b11 #
1!
#80000
0!
#85000
b101 ,
b101 7
b101 A
b1000000000000001100000 0
b1000000000000001100000 ;
b1000000000000001100000 H
b101 -
b101 @
b101 J
b10000000000000011 .
b10000000000000011 8
b10000000000000011 I
b1101 F
b1110 G
b1111 E
b111001101001011110110011 '
b111001101001011110110011 *
b111001101001011110110011 +
b111001101001011110110011 <
b10000 (
b10000 )
b10000 6
b10100 B
b10000 1
b10000 C
b10000 D
b100 #
1!
#90000
0!
#95000
b10000000000011100 ,
b10000000000011100 7
b10000000000011100 A
b10000000000011100 -
b10000000000011100 @
b10000000000011100 J
b10000000000001100 .
b10000000000001100 8
b10000000000001100 I
b1 0
b1 ;
b1 H
b10000 F
b10001 G
b10010 E
b10 3
b10 :
b10 =
b1000110000010100100110011 '
b1000110000010100100110011 *
b1000110000010100100110011 +
b1000110000010100100110011 <
b10100 (
b10100 )
b10100 6
b11000 B
b10100 1
b10100 C
b10100 D
b101 #
1!
#100000
0!
#105000
b10001000100010001000100010001 ,
b10001000100010001000100010001 7
b10001000100010001000100010001 A
b10001000100010001000100010001 -
b10001000100010001000100010001 @
b10001000100010001000100010001 J
b0 .
b0 8
b0 I
b10001000100010001000100010001 0
b10001000100010001000100010001 ;
b10001000100010001000100010001 H
b10100 F
b10011 G
b10101 E
b100 3
b100 :
b100 =
b1001110100100101010110011 '
b1001110100100101010110011 *
b1001110100100101010110011 +
b1001110100100101010110011 <
b11000 (
b11000 )
b11000 6
b11100 B
b11000 1
b11000 C
b11000 D
b110 #
1!
#110000
0!
#115000
b10001000100010001000100010011 0
b10001000100010001000100010011 ;
b10001000100010001000100010011 H
b10 ,
b10 7
b10 A
b10 -
b10 @
b10 J
b10001000100010001000100010001 .
b10001000100010001000100010001 8
b10001000100010001000100010001 I
b10101 F
b10110 G
b10111 E
b110 3
b110 :
b110 =
b1011010101110101110110011 '
b1011010101110101110110011 *
b1011010101110101110110011 +
b1011010101110101110110011 <
b11100 (
b11100 )
b11100 6
b100000 B
b11100 1
b11100 C
b11100 D
b111 #
1!
#120000
0!
#125000
b1010 ,
b1010 7
b1010 A
b1010 -
b1010 @
b1010 J
b10001000100010001000100010011 .
b10001000100010001000100010011 8
b10001000100010001000100010011 I
b10 0
b10 ;
b10 H
b10111 F
b11000 G
b11001 E
b111 3
b111 :
b111 =
b1100010111111110010110011 '
b1100010111111110010110011 *
b1100010111111110010110011 +
b1100010111111110010110011 <
b100000 (
b100000 )
b100000 6
b100100 B
b100000 1
b100000 C
b100000 D
b1000 #
1!
#130000
0!
#135000
b101100 ,
b101100 7
b101100 A
b101100 -
b101100 @
b101100 J
b11100 .
b11100 8
b11100 I
b11111111111111111111111111110000 0
b11111111111111111111111111110000 ;
b11111111111111111111111111110000 H
b11011 F
b11100 G
b11101 E
b100000 2
b100000 9
b100000 >
b0 3
b0 :
b0 =
b1000001110011011000111010110011 '
b1000001110011011000111010110011 *
b1000001110011011000111010110011 +
b1000001110011011000111010110011 <
b100100 (
b100100 )
b100100 6
b101000 B
b100100 1
b100100 C
b100100 D
b1001 #
1!
#140000
0!
#145000
b11111111111111111111111111110000 ,
b11111111111111111111111111110000 7
b11111111111111111111111111110000 A
b111100 0
b111100 ;
b111100 H
b11111111111111111111111111110000 -
b11111111111111111111111111110000 @
b11111111111111111111111111110000 J
b101100 .
b101100 8
b101100 I
b11100 F
b11101 G
b11110 E
b1000001110111100000111100110011 '
b1000001110111100000111100110011 *
b1000001110111100000111100110011 +
b1000001110111100000111100110011 <
b101000 (
b101000 )
b101000 6
b101100 B
b101000 1
b101000 C
b101000 D
b1010 #
1!
#150000
0!
#155000
b1011 -
b1011 @
b1011 J
b1010 .
b1010 8
b1010 I
b1111 0
b1111 ;
b1111 H
b101 ,
b101 7
b101 A
b101 5
b101 ?
b100 F
b101 G
b110 E
b0 2
b0 9
b0 >
14
b10100100000001100010011 '
b10100100000001100010011 *
b10100100000001100010011 +
b10100100000001100010011 <
b101100 (
b101100 )
b101100 6
b110000 B
b101100 1
b101100 C
b101100 D
b1011 #
1!
#160000
0!
#165000
b11001 0
b11001 ;
b11001 H
b1010 ,
b1010 7
b1010 A
b1111000000000001000000 -
b1111000000000001000000 @
b1111000000000001000000 J
b1111 .
b1111 8
b1111 I
b1010 5
b1010 ?
b110 F
b1010 G
b111 E
b101000110000001110010011 '
b101000110000001110010011 *
b101000110000001110010011 +
b101000110000001110010011 <
b110000 (
b110000 )
b110000 6
b110100 B
b110000 1
b110000 C
b110000 D
b1100 #
1!
#170000
0!
#175000
b110010 ,
b110010 7
b110010 A
b1 -
b1 @
b1 J
b11001 .
b11001 8
b11001 I
b1 0
b1 ;
b1 H
b110010 5
b110010 ?
b111 F
b10010 G
b1000 E
b1 2
b1 9
b1 >
b10 3
b10 :
b10 =
b11001000111010010000010011 '
b11001000111010010000010011 *
b11001000111010010000010011 +
b11001000111010010000010011 <
b110100 (
b110100 )
b110100 6
b111000 B
b110100 1
b110100 C
b110100 D
b1101 #
1!
#180000
0!
#185000
b0 0
b0 ;
b0 H
b10100 ,
b10100 7
b10100 A
b0 -
b0 @
b0 J
b10100 5
b10100 ?
b10100 G
b0 2
b0 9
b0 >
b1010000111010010000010011 '
b1010000111010010000010011 *
b1010000111010010000010011 +
b1010000111010010000010011 <
b111000 (
b111000 )
b111000 6
b111100 B
b111000 1
b111000 C
b111000 D
b1110 #
1!
#190000
0!
#195000
b0 ,
b0 7
b0 A
b11001 0
b11001 ;
b11001 H
b0 5
b0 ?
b0 G
b100 3
b100 :
b100 =
b111100010000010011 '
b111100010000010011 *
b111100010000010011 +
b111100010000010011 <
b111100 (
b111100 )
b111100 6
b1000000 B
b111100 1
b111100 C
b111100 D
b1111 #
1!
#200000
0!
#205000
b1001 E
b110 3
b110 :
b110 =
b111110010010010011 '
b111110010010010011 *
b111110010010010011 +
b111110010010010011 <
b1000000 (
b1000000 )
b1000000 6
b1000100 B
b1000000 1
b1000000 C
b1000000 D
b10000 #
1!
#210000
0!
#215000
b0 0
b0 ;
b0 H
b1010 E
b111 3
b111 :
b111 =
b111111010100010011 '
b111111010100010011 *
b111111010100010011 +
b111111010100010011 <
b1000100 (
b1000100 )
b1000100 6
b1001000 B
b1000100 1
b1000100 C
b1000100 D
b10001 #
1!
#220000
0!
#225000
b0 .
b0 8
b0 I
b0 F
b0 E
b100000 $
b10 %
b0 '
b0 *
b0 +
b0 <
b1001000 (
b1001000 )
b1001000 6
b1001100 B
b1001000 1
b1001000 C
b1001000 D
b10010 #
1!
