RTL/MEM/imem.v
//Verilog code for Instruction Memory

module imem(

input wire [31:0] ip_instr_addr_from_proc,
output reg [31:0] op_instr_from_imem,
output reg op_instr_valid
);

//Memory to hold the instructions

reg [31:0] mem[31:0];

//Reading instruction is harmless and it doesn't need any control signal
always @(*) begin: imem_block
	op_instr_from_imem= mem[ip_instr_addr_from_proc [31:2]];
	op_instr_valid =1'b1;
end

endmodule

RTL/CORES/Reg_Imm_Mem/register_file.v
// Feb 10, 2023
// Verilog Code for Register File

module regfile( 

input wire [4:0] reg_src1,
input wire [4:0] reg_src2,
input wire [4:0] reg_dest,
input wire [31:0] write_back,
input wire clk,
input wire rst,
input wire write_en,
output reg [31:0] read_data1,
output reg [31:0] read_data2
);

//32 Registers of each 32 bit
reg [31:0] mem[31:0];

//Reading from register file is harmless so no need of the control signal

always @(*) begin
	read_data1=mem[reg_src1];
	read_data2=mem[reg_src2];
end

always @(posedge clk ) begin: register_file_block
	if (write_en) begin
		mem[reg_dest] <= write_back;
	end
	
	//0th Register always holds value 0's
	mem[0] <= 'b0;
end


//always @(posedge clk or posedge rst) begin: register_file_block
//	if (rst) begin
//		mem <= 'b0;
//	end
//	else begin
//	 	if (write_en) begin
//			mem[reg_dst] <= write_back;
//		end
//	end
//	//0th Register always holds value 0's
//	mem[0] <= 'b0;
//end

endmodule

RTL/CORES/Reg_Imm_Mem_Beq_v2/mux_32.v
//Verilog Module for 32 bit Mux Logic


module mux_32(
input wire [31:0] inp0,
input wire [31:0] inp1,
input wire sel,
output reg [31:0] out
);

always @(*) begin
	if (sel) 
		out = inp1;
	else
		out = inp0;
end
endmodule

RTL/MEM/dmem.v
//Verilog Code for Data Memory

module dmem (
	input wire clk,
	input wire ip_mem_read,
	input wire ip_mem_write,

	input wire [31:0] ip_mem_addr,
	input wire [31:0] ip_mem_data,

	output reg [31:0] op_mem_out,
	output reg  op_mem_data_valid
);

//Actual Data Memory
reg [31:0] mem[31:0];

always @(*) begin : dmem_read_block
	if (ip_mem_read) begin
		op_mem_out = mem[ip_mem_addr[31:2]];
		op_mem_data_valid = 1'b1;
	end
end

always @(posedge clk) begin : dmem_write_block
	if (ip_mem_write) begin
		mem[ip_mem_addr[31:2]] <= ip_mem_data;
	end
end

endmodule

BRANCH_CASES/Reg_Imm_Mem_Beq/alu.v
//Verilog Code for ALU

module alu(

input wire [31:0] read_data1,
input wire [31:0] read_data2,
input wire [2:0] funct3,
input wire [6:0] funct7,
output reg [31:0] result
);

always @(*) begin: ALU_Block
	case (funct3)
		3'b000 :
		begin	
			if (funct7 != 7'b0100000)
				result = read_data1 + read_data2;   //ADD
			else
				result = read_data1 - read_data2;   //SUB 
		end
		3'b001 : result = read_data1 << read_data2;  //Shift Logical Left
		3'b010 : 				     //Set Less Than		
			if (read_data1 < read_data2) begin
				result = 1;
			end
			else begin 
				result = 0;
			end
		3'b011 :				     //S.L.T.Unsigned
 			if (read_data1 < read_data2) begin
				result = 1;
			end
			else begin 
				result = 0;
			end
		3'b100 : result = (read_data1 ^ read_data2); //XOR
		3'b101 :
		begin
			if (funct7 != 7'b0100000) 	
				result = read_data1 >> read_data2;  //Shift Right Logical
			else
				result = read_data1 >>> read_data2; //Shift Right Arithmetic
		end	
		3'b110 : result = read_data1 | read_data2;  //OR
		3'b111 : result = read_data1 & read_data2;  //AND
		default: result = 'b0;
	endcase
	
end
endmodule

BRANCH_CASES/Reg_Imm_Mem_Beq/adder.v
//Verilog Module for Adder Specifically for Conditional Branch

module adder (
	input wire [31:0] inp1,
	input wire [31:0] inp2,
	output reg [31:0] res
);

always @(*) begin
	res = inp1 + inp2;
end

endmodule

BRANCH_CASES/Reg_Imm_Mem_Beq/decoder.v
//Verilog code for the Decoder- to generate control signals.

module decoder(

input wire [31:0] ip_instr_from_imem,
input wire ip_instr_valid,
output reg reg_write,
output reg [2:0] funct3,
output reg [6:0] funct7,
output reg alu_src_from_imem,
output reg mem_read,
output reg mem_write,
output reg mem_to_reg,
output reg [31:0] imem_sign_ext,
output reg beq,
output reg bne,
output reg blt,
output reg bge
);

always @(*) begin:decoder_block
	if (ip_instr_valid) begin
		case (ip_instr_from_imem[6:0]) 
			7'b0110011: //R-type Instruction 
			begin
				reg_write=1'b1;
			        alu_src_from_imem = 1'b0;	
				//3bit-Opcode
				funct3=ip_instr_from_imem[14:12];
				//7bit-Functionality
				funct7=ip_instr_from_imem[31:25];
				mem_read = 1'b0;
				mem_write = 1'b0;
				mem_to_reg = 1'b0;
			 	imem_sign_ext = 32'b0;

				beq = 1'b0;
				bne = 1'b0;
				blt = 1'b0;
				bge = 1'b0;
			end

			7'b0010011: //Immediate Type Instruction
			begin
				alu_src_from_imem = 1'b1;
				reg_write = 1'b1;
				//3bit-Opcode
				funct3 = ip_instr_from_imem[14:12];	
				//7bit-Functionality
				funct7 = ip_instr_from_imem[31:25];
				mem_read = 1'b0;
				mem_write = 1'b0;
				mem_to_reg = 1'b0;
				if ((funct3 != 3'b001) && (funct3 != 3'b101))
					imem_sign_ext = {{20{ip_instr_from_imem[31]}}, ip_instr_from_imem[31:20]};
				else
					imem_sign_ext = {{20{1'b0}}, {7{1'b0}}, ip_instr_from_imem[24:20]};

				beq = 1'b0;
				bne = 1'b0;
				blt = 1'b0;
				bge = 1'b0;
			end

			7'b0000011: //Load Word
			begin
				alu_src_from_imem = 1'b1;
				reg_write = 1'b1;
				//funct3 = ip_instr_from_imem[14:12];
				funct3 = 3'b000;
				funct7 = 7'b0;
				mem_read = 1'b1;
				mem_write = 1'b0;
				mem_to_reg = 1'b1;
				imem_sign_ext = {{20{ip_instr_from_imem[31]}}, ip_instr_from_imem[31:20]};

				beq = 1'b0;
				bne = 1'b0;
				blt = 1'b0;
				bge = 1'b0;
			end

			7'b0100011: //Store Word
			begin
				alu_src_from_imem = 1'b1;
				reg_write = 1'b0;
				//funct3 = ip_instr_from_imem[14:12];
				funct3 = 3'b000;
				funct7 = 7'b0;
				mem_read = 1'b0;
				mem_write = 1'b1;
				mem_to_reg = 1'bx;
				imem_sign_ext = {{20{ip_instr_from_imem[31]}}, ip_instr_from_imem[31:25], ip_instr_from_imem[11:7]};

				beq = 1'b0;
				bne = 1'b0;
				blt = 1'b0;
				bge = 1'b0;
			end

			7'b1100011: //Controlled Branches
			begin
				alu_src_from_imem = 1'b0;
				reg_write = 1'b0;
				funct3 = 3'b000;
				funct7 = 7'b0100000;
				mem_read = 1'b0;
				mem_write = 1'b0;
				mem_to_reg = 1'bx;
				imem_sign_ext = {{20{ip_instr_from_imem[31]}}, ip_instr_from_imem[7], ip_instr_from_imem[30:25], ip_instr_from_imem[11:8], 1'b0};
				
				case (ip_instr_from_imem[14:12])
					3'b000:
					begin
						beq = 1'b1;
						bne = 1'b0;
						blt = 1'b0;
						bge = 1'b0;
					end

					3'b001:
					begin
						beq = 1'b0;
						bne = 1'b1;
						blt = 1'b0;
						bge = 1'b0;
					end

					3'b100:
					begin
						beq = 1'b0;
						bne = 1'b0;
						blt = 1'b1;
						bge = 1'b0;
					end
					
					3'b101:
					begin
						beq = 1'b0;
						bne = 1'b0;
						blt = 1'b0;
						bge = 1'b1;
					end
				endcase						
			end
		endcase
	end

end
endmodule

RTL/CORES/Reg_Imm_Mem_Beq_v2/processor_v1.v
//Verilog Code for single cycle processor

module processor_v1(

//General inputs
input wire clk,
input wire rst,

//Inputs and Outputs from imem 
input wire [31:0] ip_instr_from_imem,
input wire ip_instr_valid,
output reg [31:0] op_instr_addr_from_proc

);

wire [31:0] read_data1;
wire [31:0] read_data2;
wire [31:0] alu_output;
wire [31:0] wb_data;

//wires to and from Decoder Module
wire alu_src_from_imem;
wire [2:0] funct3;
wire [6:0] funct7;
wire op_data_wr;
wire mem_read_en;
wire mem_write_en;
wire mem_to_reg_en;
wire [31:0] imem_sign_ext;
wire beq;
wire bne;
wire blt;
wire bge;

wire [31:0] mem_out;
wire mem_out_valid;

//wire op_instr_addr_from_proc;
wire [31:0] ip_instr_addr_from_pc;

// intermediate signals wrt immediate instr
wire [31:0] read_data_from_mux;
wire [31:0] target_addr;

reg [31:0] pc;
reg [31:0] next_pc;
wire [31:0] new_pc;

reg mux_en_bta;

always @(posedge clk) begin
	if (rst) begin
		pc <= 0;

	end
	else begin
		pc <= new_pc;
	end
end

always @(*) begin
	next_pc = pc + 32'h4;
	op_instr_addr_from_proc = pc;
	mux_en_bta = beq & (alu_output == 0);
end

decoder dec_0 (
	.ip_instr_from_imem(ip_instr_from_imem),  
	.funct3(funct3), //control signal for ALU
	.funct7(funct7), //control signal for ALU
	.ip_instr_valid(ip_instr_valid), //instr is valid or not
	.reg_write(op_data_wr), //register wrtie instr or not
	.alu_src_from_imem(alu_src_from_imem), //reading either from reg_file or immediate data
	.mem_read(mem_read_en),
	.mem_write(mem_write_en),
	.mem_to_reg(mem_to_reg_en),
	.imem_sign_ext(imem_sign_ext),
	.beq(beq),
	.bne(bne),
	.blt(blt),
	.bge(bge)
);

adder adder_0 (
	.inp1(pc),
	.inp2(imem_sign_ext),
	.res(target_addr)
);

alu alu_0 (
	.read_data1(read_data1), //read data1 
	.read_data2(read_data_from_mux), //read data either from reg_file or immediate
	.funct3(funct3), 
	.funct7(funct7), 
	.result(alu_output) //final result from ALU
);

dmem dmem_0 (
	.clk(clk),
	.ip_mem_read(mem_read_en),
	.ip_mem_write(mem_write_en),
	.ip_mem_addr(alu_output),
	.ip_mem_data(read_data2),
	.op_mem_out(mem_out),
	.op_mem_data_valid(mem_out_valid)
);

mux_32 mux_32_0 (
	.inp0(read_data2),
	.inp1(imem_sign_ext),
	.sel(alu_src_from_imem),
	.out(read_data_from_mux)
);

mux_32 mux_32_1 (
	.inp0(alu_output),
	.inp1(mem_out),
	.sel(mem_to_reg_en),
	.out(wb_data)
);

mux_32 mux_32_2 (
	.inp0(next_pc),
	.inp1(target_addr),
	.sel(mux_en_bta),
	.out(new_pc)
);	

regfile regfile_0 (
	.reg_src1(ip_instr_from_imem[19:15]), //reg_source 1
	.reg_src2(ip_instr_from_imem[24:20]), //reg_source 2
	.reg_dest(ip_instr_from_imem[11:7]),  //reg_dest
	.write_back(wb_data), //data to be written
	.clk(clk), 
	.rst(rst), 
	.write_en(op_data_wr), //to write into reg_file if its a reg_write instr
	.read_data1(read_data1), //data from reg_source1
	.read_data2(read_data2) //data from reg_source2
);

endmodule

RTL/SoC.v
//Top Module which instantiate Memory Modules and Processor 

module SoC (
	//General Inputs
	input wire clk,
	input wire rst
);

wire [31:0] instr_addr_from_proc; 


wire [31:0] instr_from_imem;
wire instr_valid_from_imem;

//Instantiation of Processor and IMEM

processor_v1 processor_v1_0 (
	.clk(clk), 
	.rst(rst), 
	.ip_instr_from_imem(instr_from_imem), 
	.ip_instr_valid(instr_valid_from_imem), 
	.op_instr_addr_from_proc(instr_addr_from_proc)
);

imem imem_0 (
.ip_instr_addr_from_proc(instr_addr_from_proc), 
.op_instr_from_imem(instr_from_imem), 
.op_instr_valid(instr_valid_from_imem)
);

endmodule

TESTS/003_MemType_tests/tb.v
//Verilog Code for testing the Processor

//TestBench- Inputs and Outputs which you are giving and viewing respectively.
//Also to facilitate instantiation between two or more instants of module
//(Primarly taking and giving values between instanted modules)

`timescale 1ns/1ps

module tb;

reg clk;
reg rst;

//Clock
always #5 clk = ~clk;

//To count number of clocks
integer clock;

//To open the reg file and to dump data into it
integer reg_file_contents;
integer mem_file_contents;
integer i;

initial begin

	//Dumping values into VCD using system_task for plotting signals
	$dumpfile("wave.vcd");

	//Dumping all the top level signal of the test bench- scope:0 
	$dumpvars(0, tb);
	
	//Storing the values from imem file to imem memory
	$readmemh("imem.fill", SoC_0.imem_0.mem);
	$readmemh("dmem.fill", SoC_0.processor_v1_0.dmem_0.mem);
	$readmemh("rf.fill", SoC_0.processor_v1_0.regfile_0.mem);
	
	//Resetting the Values
	clk <= 0;
	rst <= 1;
	clock <= 0;

	//After 5 negedge make reset 0
	@(negedge clk);

	repeat(5) begin 
		@(negedge clk);
	end
	
	rst <= 0;

	//Once the reset is 0, the program will run and by fetching the
	//instruction all 32 bit 0 indicated the end of the program.
	wait(SoC_0.instr_from_imem == 32'b0);
	$display("The program completed in the %d clock cycles", clock);

	////Draining pipeline
	//repeat(5) @(negedge clk);

	//Dump all the content in the registers into the file with dump
	//extenstion
	reg_file_contents=$fopen("rf_values.dump");

	for(i=0; i<32 ; i=i+1) begin
		$fdisplay(reg_file_contents,"Register %d : %h", i, SoC_0.processor_v1_0.regfile_0.mem[i]);
	end
	$fclose(reg_file_contents);

	mem_file_contents=$fopen("dmem_values.dump");

	for(i=0; i<32; i=i+1) begin
		$fdisplay(mem_file_contents,"Memory %d : %h", i, SoC_0.processor_v1_0.dmem_0.mem[i]);
	end
	$fclose(mem_file_contents);

	$finish;
end

always @(posedge clk) begin
	if (rst) begin
		clock <= 0;
	end
	else begin
		clock <= clock + 1;
	end
end

//To avoid infinte loops
initial begin
	#1000
	$display("Test timeout, there should be infinite loop!!! Please check");
	$finish;
end

//Instantiation of SoC

SoC SoC_0 (
	.clk(clk),
	.rst(rst)
);

endmodule

TESTS/004_Branch_tests_v2/wave.vcd
$date
	Wed Apr  5 14:40:58 2023
$end
$version
	Icarus Verilog
$end
$timescale
	1ps
$end
$scope module tb $end
$var reg 1 ! clk $end
$var reg 1 " rst $end
$var integer 32 # clock [31:0] $end
$var integer 32 $ i [31:0] $end
$var integer 32 % mem_file_contents [31:0] $end
$var integer 32 & reg_file_contents [31:0] $end
$scope module SoC_0 $end
$var wire 1 ! clk $end
$var wire 1 " rst $end
$var wire 1 ' instr_valid_from_imem $end
$var wire 32 ( instr_from_imem [31:0] $end
$var wire 32 ) instr_addr_from_proc [31:0] $end
$scope module imem_0 $end
$var wire 32 * ip_instr_addr_from_proc [31:0] $end
$var reg 32 + op_instr_from_imem [31:0] $end
$var reg 1 ' op_instr_valid $end
$scope begin imem_block $end
$upscope $end
$upscope $end
$scope module processor_v1_0 $end
$var wire 1 ! clk $end
$var wire 32 , ip_instr_from_imem [31:0] $end
$var wire 1 ' ip_instr_valid $end
$var wire 1 " rst $end
$var wire 32 - wb_data [31:0] $end
$var wire 32 . target_addr [31:0] $end
$var wire 32 / read_data_from_mux [31:0] $end
$var wire 32 0 read_data2 [31:0] $end
$var wire 32 1 read_data1 [31:0] $end
$var wire 1 2 op_data_wr $end
$var wire 32 3 new_pc [31:0] $end
$var wire 1 4 mem_write_en $end
$var wire 1 5 mem_to_reg_en $end
$var wire 1 6 mem_read_en $end
$var wire 1 7 mem_out_valid $end
$var wire 32 8 mem_out [31:0] $end
$var wire 32 9 imem_sign_ext [31:0] $end
$var wire 7 : funct7 [6:0] $end
$var wire 3 ; funct3 [2:0] $end
$var wire 1 < bne $end
$var wire 1 = blt $end
$var wire 1 > bge $end
$var wire 1 ? beq $end
$var wire 1 @ alu_src_from_imem $end
$var wire 32 A alu_output [31:0] $end
$var reg 1 B mux_en_bta $end
$var reg 32 C next_pc [31:0] $end
$var reg 32 D op_instr_addr_from_proc [31:0] $end
$var reg 32 E pc [31:0] $end
$scope module adder_0 $end
$var wire 32 F inp1 [31:0] $end
$var wire 32 G inp2 [31:0] $end
$var reg 32 H res [31:0] $end
$upscope $end
$scope module alu_0 $end
$var wire 32 I read_data2 [31:0] $end
$var wire 32 J read_data1 [31:0] $end
$var wire 7 K funct7 [6:0] $end
$var wire 3 L funct3 [2:0] $end
$var reg 32 M result [31:0] $end
$scope begin ALU_Block $end
$upscope $end
$upscope $end
$scope module dec_0 $end
$var wire 32 N ip_instr_from_imem [31:0] $end
$var wire 1 ' ip_instr_valid $end
$var reg 1 @ alu_src_from_imem $end
$var reg 1 ? beq $end
$var reg 1 > bge $end
$var reg 1 = blt $end
$var reg 1 < bne $end
$var reg 3 O funct3 [2:0] $end
$var reg 7 P funct7 [6:0] $end
$var reg 32 Q imem_sign_ext [31:0] $end
$var reg 1 6 mem_read $end
$var reg 1 5 mem_to_reg $end
$var reg 1 4 mem_write $end
$var reg 1 2 reg_write $end
$scope begin decoder_block $end
$upscope $end
$upscope $end
$scope module dmem_0 $end
$var wire 1 ! clk $end
$var wire 32 R ip_mem_addr [31:0] $end
$var wire 1 6 ip_mem_read $end
$var wire 1 4 ip_mem_write $end
$var wire 32 S ip_mem_data [31:0] $end
$var reg 1 7 op_mem_data_valid $end
$var reg 32 T op_mem_out [31:0] $end
$scope begin dmem_read_block $end
$upscope $end
$scope begin dmem_write_block $end
$upscope $end
$upscope $end
$scope module mux_32_0 $end
$var wire 32 U inp1 [31:0] $end
$var wire 1 @ sel $end
$var wire 32 V inp0 [31:0] $end
$var reg 32 W out [31:0] $end
$upscope $end
$scope module mux_32_1 $end
$var wire 32 X inp0 [31:0] $end
$var wire 32 Y inp1 [31:0] $end
$var wire 1 5 sel $end
$var reg 32 Z out [31:0] $end
$upscope $end
$scope module mux_32_2 $end
$var wire 32 [ inp0 [31:0] $end
$var wire 32 \ inp1 [31:0] $end
$var wire 1 B sel $end
$var reg 32 ] out [31:0] $end
$upscope $end
$scope module regfile_0 $end
$var wire 1 ! clk $end
$var wire 5 ^ reg_dest [4:0] $end
$var wire 5 _ reg_src1 [4:0] $end
$var wire 5 ` reg_src2 [4:0] $end
$var wire 1 " rst $end
$var wire 32 a write_back [31:0] $end
$var wire 1 2 write_en $end
$var reg 32 b read_data1 [31:0] $end
$var reg 32 c read_data2 [31:0] $end
$scope begin register_file_block $end
$upscope $end
$upscope $end
$upscope $end
$upscope $end
$upscope $end
$enddefinitions $end
#0
$dumpvars
bx c
bx b
bx a
bx `
bx _
bx ^
bx ]
bx \
bx [
bx Z
bx Y
bx X
bx W
bx V
bx U
bx T
bx S
bx R
bx Q
bx P
bx O
bx N
bx M
bx L
bx K
bx J
bx I
bx H
bx G
bx F
bx E
bx D
bx C
xB
bx A
x@
x?
x>
x=
x<
bx ;
bx :
bx 9
bx 8
x7
x6
x5
x4
bx 3
x2
bx 1
bx 0
bx /
bx .
bx -
bx ,
bx +
bx *
bx )
bx (
1'
bx &
bx %
bx $
b0 #
1"
0!
$end
#5000
b110110 -
b110110 Z
b110110 a
b110110 A
b110110 M
b110110 R
b110110 X
b101100 /
b101100 I
b101100 W
b101100 0
b101100 S
b101100 V
b101100 c
b1010 1
b1010 J
b1010 b
0B
b0 .
b0 H
b0 \
b100 _
b1000 `
b11 ^
0>
0=
0<
0?
b0 9
b0 G
b0 Q
b0 U
05
04
06
b0 :
b0 K
b0 P
b0 ;
b0 L
b0 O
0@
12
b100000100000000110110011 (
b100000100000000110110011 +
b100000100000000110110011 ,
b100000100000000110110011 N
b100 3
b100 ]
b0 )
b0 *
b0 D
b100 C
b100 [
b0 E
b0 F
1!
#10000
0!
#15000
1!
#20000
0!
#25000
1!
#30000
0!
#35000
1!
#40000
0!
#45000
1!
#50000
0"
0!
#55000
b11 -
b11 Z
b11 a
b10 /
b10 I
b10 W
b11 A
b11 M
b11 R
b11 X
b10 0
b10 S
b10 V
b10 c
b1 1
b1 J
b1 b
b1 _
b10 `
b10 ^
b1000001000000100110011 (
b1000001000000100110011 +
b1000001000000100110011 ,
b1000001000000100110011 N
b1000 3
b1000 ]
b100 .
b100 H
b100 \
b100 )
b100 *
b100 D
b1000 C
b1000 [
b1 #
b100 E
b100 F
1!
#60000
0!
#65000
b111001 -
b111001 Z
b111001 a
b11 1
b11 J
b11 b
b111001 A
b111001 M
b111001 R
b111001 X
b10 _
b11 `
b1000 ^
b110110 /
b110110 I
b110110 W
b1100010000010000110011 (
b1100010000010000110011 +
b1100010000010000110011 ,
b1100010000010000110011 N
b1100 3
b1100 ]
b110110 0
b110110 S
b110110 V
b110110 c
b1000 .
b1000 H
b1000 \
b1000 )
b1000 *
b1000 D
b1100 C
b1100 [
b1000 E
b1000 F
b10 #
1!
#70000
0!
#75000
b110 /
b110 I
b110 W
b1111000000000001000000 -
b1111000000000001000000 Z
b1111000000000001000000 a
b110 0
b110 S
b110 V
b110 c
b1111000000000001 1
b1111000000000001 J
b1111000000000001 b
b1111000000000001000000 A
b1111000000000001000000 M
b1111000000000001000000 R
b1111000000000001000000 X
b1011 _
b1100 `
b1010 ^
b1 ;
b1 L
b1 O
b110001011001010100110011 (
b110001011001010100110011 +
b110001011001010100110011 ,
b110001011001010100110011 N
b10000 3
b10000 ]
b1100 .
b1100 H
b1100 \
b1100 )
b1100 *
b1100 D
b10000 C
b10000 [
b11 #
b1100 E
b1100 F
1!
#80000
0!
#85000
b1000000000000001100000 -
b1000000000000001100000 Z
b1000000000000001100000 a
b101 /
b101 I
b101 W
b1000000000000001100000 A
b1000000000000001100000 M
b1000000000000001100000 R
b1000000000000001100000 X
b101 0
b101 S
b101 V
b101 c
b10000000000000011 1
b10000000000000011 J
b10000000000000011 b
b1101 _
b1110 `
b1111 ^
b111001101001011110110011 (
b111001101001011110110011 +
b111001101001011110110011 ,
b111001101001011110110011 N
b10100 3
b10100 ]
b10000 .
b10000 H
b10000 \
b10000 )
b10000 *
b10000 D
b10100 C
b10100 [
b10000 E
b10000 F
b100 #
1!
#90000
0!
#95000
b10000000000011100 /
b10000000000011100 I
b10000000000011100 W
b1 -
b1 Z
b1 a
b10000000000011100 0
b10000000000011100 S
b10000000000011100 V
b10000000000011100 c
b10000000000001100 1
b10000000000001100 J
b10000000000001100 b
b1 A
b1 M
b1 R
b1 X
b10000 _
b10001 `
b10010 ^
b10 ;
b10 L
b10 O
b1000110000010100100110011 (
b1000110000010100100110011 +
b1000110000010100100110011 ,
b1000110000010100100110011 N
b11000 3
b11000 ]
b10100 .
b10100 H
b10100 \
b10100 )
b10100 *
b10100 D
b11000 C
b11000 [
b101 #
b10100 E
b10100 F
1!
#100000
0!
#105000
b10001000100010001000100010001 /
b10001000100010001000100010001 I
b10001000100010001000100010001 W
b10001000100010001000100010001 -
b10001000100010001000100010001 Z
b10001000100010001000100010001 a
b10001000100010001000100010001 0
b10001000100010001000100010001 S
b10001000100010001000100010001 V
b10001000100010001000100010001 c
b0 1
b0 J
b0 b
b10001000100010001000100010001 A
b10001000100010001000100010001 M
b10001000100010001000100010001 R
b10001000100010001000100010001 X
b10100 _
b10011 `
b10101 ^
b100 ;
b100 L
b100 O
b1001110100100101010110011 (
b1001110100100101010110011 +
b1001110100100101010110011 ,
b1001110100100101010110011 N
b11100 3
b11100 ]
b11000 .
b11000 H
b11000 \
b11000 )
b11000 *
b11000 D
b11100 C
b11100 [
b11000 E
b11000 F
b110 #
1!
#110000
0!
#115000
b10001000100010001000100010011 -
b10001000100010001000100010011 Z
b10001000100010001000100010011 a
b10001000100010001000100010011 A
b10001000100010001000100010011 M
b10001000100010001000100010011 R
b10001000100010001000100010011 X
b10 /
b10 I
b10 W
b10 0
b10 S
b10 V
b10 c
b10001000100010001000100010001 1
b10001000100010001000100010001 J
b10001000100010001000100010001 b
b10101 _
b10110 `
b10111 ^
b110 ;
b110 L
b110 O
b1011010101110101110110011 (
b1011010101110101110110011 +
b1011010101110101110110011 ,
b1011010101110101110110011 N
b100000 3
b100000 ]
b11100 .
b11100 H
b11100 \
b11100 )
b11100 *
b11100 D
b100000 C
b100000 [
b111 #
b11100 E
b11100 F
1!
#120000
0!
#125000
b1010 /
b1010 I
b1010 W
b10 -
b10 Z
b10 a
b1010 0
b1010 S
b1010 V
b1010 c
b10001000100010001000100010011 1
b10001000100010001000100010011 J
b10001000100010001000100010011 b
b10 A
b10 M
b10 R
b10 X
b10111 _
b11000 `
b11001 ^
b111 ;
b111 L
b111 O
b1100010111111110010110011 (
b1100010111111110010110011 +
b1100010111111110010110011 ,
b1100010111111110010110011 N
b100100 3
b100100 ]
b100000 .
b100000 H
b100000 \
b100000 )
b100000 *
b100000 D
b100100 C
b100100 [
b100000 E
b100000 F
b1000 #
1!
#130000
0!
#135000
b101100 /
b101100 I
b101100 W
b11111111111111111111111111110000 -
b11111111111111111111111111110000 Z
b11111111111111111111111111110000 a
b101100 0
b101100 S
b101100 V
b101100 c
b11100 1
b11100 J
b11100 b
b11111111111111111111111111110000 A
b11111111111111111111111111110000 M
b11111111111111111111111111110000 R
b11111111111111111111111111110000 X
b11011 _
b11100 `
b11101 ^
b100000 :
b100000 K
b100000 P
b0 ;
b0 L
b0 O
b1000001110011011000111010110011 (
b1000001110011011000111010110011 +
b1000001110011011000111010110011 ,
b1000001110011011000111010110011 N
b101000 3
b101000 ]
b100100 .
b100100 H
b100100 \
b100100 )
b100100 *
b100100 D
b101000 C
b101000 [
b1001 #
b100100 E
b100100 F
1!
#140000
0!
#145000
b111100 -
b111100 Z
b111100 a
b11111111111111111111111111110000 /
b11111111111111111111111111110000 I
b11111111111111111111111111110000 W
b111100 A
b111100 M
b111100 R
b111100 X
b11111111111111111111111111110000 0
b11111111111111111111111111110000 S
b11111111111111111111111111110000 V
b11111111111111111111111111110000 c
b101100 1
b101100 J
b101100 b
b11100 _
b11101 `
b11110 ^
b1000001110111100000111100110011 (
b1000001110111100000111100110011 +
b1000001110111100000111100110011 ,
b1000001110111100000111100110011 N
b101100 3
b101100 ]
b101000 .
b101000 H
b101000 \
b101000 )
b101000 *
b101000 D
b101100 C
b101100 [
b101000 E
b101000 F
b1010 #
1!
#150000
0!
#155000
b1111 -
b1111 Z
b1111 a
b1011 0
b1011 S
b1011 V
b1011 c
b1010 1
b1010 J
b1010 b
b1111 A
b1111 M
b1111 R
b1111 X
b101 /
b101 I
b101 W
b100 _
b101 `
b110 ^
b101 9
b101 G
b101 Q
b101 U
b0 :
b0 K
b0 P
1@
b10100100000001100010011 (
b10100100000001100010011 +
b10100100000001100010011 ,
b10100100000001100010011 N
b110000 3
b110000 ]
b110001 .
b110001 H
b110001 \
b101100 )
b101100 *
b101100 D
b110000 C
b110000 [
b1011 #
b101100 E
b101100 F
1!
#160000
0!
#165000
b11001 -
b11001 Z
b11001 a
b11001 A
b11001 M
b11001 R
b11001 X
b1111000000000001000000 0
b1111000000000001000000 S
b1111000000000001000000 V
b1111000000000001000000 c
b1111 1
b1111 J
b1111 b
b1010 /
b1010 I
b1010 W
b110 _
b1010 `
b111 ^
b1010 9
b1010 G
b1010 Q
b1010 U
b101000110000001110010011 (
b101000110000001110010011 +
b101000110000001110010011 ,
b101000110000001110010011 N
b110100 3
b110100 ]
b111010 .
b111010 H
b111010 \
b110000 )
b110000 *
b110000 D
b110100 C
b110100 [
b110000 E
b110000 F
b1100 #
1!
#170000
0!
#175000
b1 -
b1 Z
b1 a
b1 0
b1 S
b1 V
b1 c
b11001 1
b11001 J
b11001 b
b110010 /
b110010 I
b110010 W
b1 A
b1 M
b1 R
b1 X
b111 _
b10010 `
b1000 ^
b110010 9
b110010 G
b110010 Q
b110010 U
b1 :
b1 K
b1 P
b10 ;
b10 L
b10 O
b11001000111010010000010011 (
b11001000111010010000010011 +
b11001000111010010000010011 ,
b11001000111010010000010011 N
b111000 3
b111000 ]
b1100110 .
b1100110 H
b1100110 \
b110100 )
b110100 *
b110100 D
b111000 C
b111000 [
b1101 #
b110100 E
b110100 F
1!
#180000
0!
#185000
b0 -
b0 Z
b0 a
b0 A
b0 M
b0 R
b0 X
b0 0
b0 S
b0 V
b0 c
b10100 /
b10100 I
b10100 W
b10100 `
b10100 9
b10100 G
b10100 Q
b10100 U
b0 :
b0 K
b0 P
b1010000111010010000010011 (
b1010000111010010000010011 +
b1010000111010010000010011 ,
b1010000111010010000010011 N
b111100 3
b111100 ]
b1001100 .
b1001100 H
b1001100 \
b111000 )
b111000 *
b111000 D
b111100 C
b111100 [
b111000 E
b111000 F
b1110 #
1!
#190000
0!
#195000
b11001 -
b11001 Z
b11001 a
b0 /
b0 I
b0 W
b11001 A
b11001 M
b11001 R
b11001 X
b0 `
b0 9
b0 G
b0 Q
b0 U
b100 ;
b100 L
b100 O
b111100010000010011 (
b111100010000010011 +
b111100010000010011 ,
b111100010000010011 N
b1000000 3
b1000000 ]
b111100 .
b111100 H
b111100 \
b111100 )
b111100 *
b111100 D
b1000000 C
b1000000 [
b1111 #
b111100 E
b111100 F
1!
#200000
0!
#205000
b1001 ^
b110 ;
b110 L
b110 O
b111110010010010011 (
b111110010010010011 +
b111110010010010011 ,
b111110010010010011 N
b1000100 3
b1000100 ]
b1000000 .
b1000000 H
b1000000 \
b1000000 )
b1000000 *
b1000000 D
b1000100 C
b1000100 [
b1000000 E
b1000000 F
b10000 #
1!
#210000
0!
#215000
b0 -
b0 Z
b0 a
b0 A
b0 M
b0 R
b0 X
b1010 ^
b111 ;
b111 L
b111 O
b111111010100010011 (
b111111010100010011 +
b111111010100010011 ,
b111111010100010011 N
b1001000 3
b1001000 ]
b1000100 .
b1000100 H
b1000100 \
b1000100 )
b1000100 *
b1000100 D
b1001000 C
b1001000 [
b10001 #
b1000100 E
b1000100 F
1!
#220000
0!
#225000
b110 0
b110 S
b110 V
b110 c
b0 1
b0 J
b0 b
b1100 /
b1100 I
b1100 W
b10101011000001000101011000100000 -
b10101011000001000101011000100000 Z
b10101011000001000101011000100000 a
17
b10101011000001000101011000100000 8
b10101011000001000101011000100000 T
b10101011000001000101011000100000 Y
b1100 A
b1100 M
b1100 R
b1100 X
b1010 _
b1100 `
b1100 9
b1100 G
b1100 Q
b1100 U
15
16
b0 ;
b0 L
b0 O
b110001010010010100000011 (
b110001010010010100000011 +
b110001010010010100000011 ,
b110001010010010100000011 N
b1001100 3
b1001100 ]
b1010100 .
b1010100 H
b1010100 \
b1001000 )
b1001000 *
b1001000 D
b1001100 C
b1001100 [
b1001000 E
b1001000 F
b10010 #
1!
#230000
0!
