RTL/MEM/imem.v
//Verilog code for Instruction Memory

module imem(

input wire [31:0] ip_instr_addr_from_proc,
output reg [31:0] op_instr_from_imem,
output reg op_instr_valid
);

//Memory to hold the instructions

reg [31:0] mem[31:0];

//Reading instruction is harmless and it doesn't need any control signal
always @(*) begin: imem_block
	op_instr_from_imem= mem[ip_instr_addr_from_proc [31:2]];
	op_instr_valid =1'b1;
end

endmodule

RTL/CORES/Reg_Imm_Mem/register_file.v
// Feb 10, 2023
// Verilog Code for Register File

module regfile( 

input wire [4:0] reg_src1,
input wire [4:0] reg_src2,
input wire [4:0] reg_dest,
input wire [31:0] write_back,
input wire clk,
input wire rst,
input wire write_en,
output reg [31:0] read_data1,
output reg [31:0] read_data2
);

//32 Registers of each 32 bit
reg [31:0] mem[31:0];

//Reading from register file is harmless so no need of the control signal

always @(*) begin
	read_data1=mem[reg_src1];
	read_data2=mem[reg_src2];
end

always @(posedge clk ) begin: register_file_block
	if (write_en) begin
		mem[reg_dest] <= write_back;
	end
	
	//0th Register always holds value 0's
	mem[0] <= 'b0;
end


//always @(posedge clk or posedge rst) begin: register_file_block
//	if (rst) begin
//		mem <= 'b0;
//	end
//	else begin
//	 	if (write_en) begin
//			mem[reg_dst] <= write_back;
//		end
//	end
//	//0th Register always holds value 0's
//	mem[0] <= 'b0;
//end

endmodule

RTL/CORES/Reg_Imm_Mem_Beq_v2/mux_32.v
//Verilog Module for 32 bit Mux Logic


module mux_32(
input wire [31:0] inp0,
input wire [31:0] inp1,
input wire sel,
output reg [31:0] out
);

always @(*) begin
	if (sel) 
		out = inp1;
	else
		out = inp0;
end
endmodule

RTL/MEM/dmem.v
//Verilog Code for Data Memory

module dmem (
	input wire clk,
	input wire ip_mem_read,
	input wire ip_mem_write,

	input wire [31:0] ip_mem_addr,
	input wire [31:0] ip_mem_data,

	output reg [31:0] op_mem_out,
	output reg  op_mem_data_valid
);

//Actual Data Memory
reg [31:0] mem[31:0];

always @(*) begin : dmem_read_block
	if (ip_mem_read) begin
		op_mem_out = mem[ip_mem_addr[31:2]];
		op_mem_data_valid = 1'b1;
	end
end

always @(posedge clk) begin : dmem_write_block
	if (ip_mem_write) begin
		mem[ip_mem_addr[31:2]] <= ip_mem_data;
	end
end

endmodule

BRANCH_CASES/Reg_Imm_Mem_Beq/alu.v
//Verilog Code for ALU

module alu(

input wire [31:0] read_data1,
input wire [31:0] read_data2,
input wire [2:0] funct3,
input wire [6:0] funct7,
output reg [31:0] result
);

always @(*) begin: ALU_Block
	case (funct3)
		3'b000 :
		begin	
			if (funct7 != 7'b0100000)
				result = read_data1 + read_data2;   //ADD
			else
				result = read_data1 - read_data2;   //SUB 
		end
		3'b001 : result = read_data1 << read_data2;  //Shift Logical Left
		3'b010 : 				     //Set Less Than		
			if (read_data1 < read_data2) begin
				result = 1;
			end
			else begin 
				result = 0;
			end
		3'b011 :				     //S.L.T.Unsigned
 			if (read_data1 < read_data2) begin
				result = 1;
			end
			else begin 
				result = 0;
			end
		3'b100 : result = (read_data1 ^ read_data2); //XOR
		3'b101 :
		begin
			if (funct7 != 7'b0100000) 	
				result = read_data1 >> read_data2;  //Shift Right Logical
			else
				result = read_data1 >>> read_data2; //Shift Right Arithmetic
		end	
		3'b110 : result = read_data1 | read_data2;  //OR
		3'b111 : result = read_data1 & read_data2;  //AND
		default: result = 'b0;
	endcase
	
end
endmodule

BRANCH_CASES/Reg_Imm_Mem_Beq/adder.v
//Verilog Module for Adder Specifically for Conditional Branch

module adder (
	input wire [31:0] inp1,
	input wire [31:0] inp2,
	output reg [31:0] res
);

always @(*) begin
	res = inp1 + inp2;
end

endmodule

BRANCH_CASES/Reg_Imm_Mem_Beq/decoder.v
//Verilog code for the Decoder- to generate control signals.

module decoder(

input wire [31:0] ip_instr_from_imem,
input wire ip_instr_valid,
output reg reg_write,
output reg [2:0] funct3,
output reg [6:0] funct7,
output reg alu_src_from_imem,
output reg mem_read,
output reg mem_write,
output reg mem_to_reg,
output reg [31:0] imem_sign_ext,
output reg beq,
output reg bne,
output reg blt,
output reg bge
);

always @(*) begin:decoder_block
	if (ip_instr_valid) begin
		case (ip_instr_from_imem[6:0]) 
			7'b0110011: //R-type Instruction 
			begin
				reg_write=1'b1;
			        alu_src_from_imem = 1'b0;	
				//3bit-Opcode
				funct3=ip_instr_from_imem[14:12];
				//7bit-Functionality
				funct7=ip_instr_from_imem[31:25];
				mem_read = 1'b0;
				mem_write = 1'b0;
				mem_to_reg = 1'b0;
			 	imem_sign_ext = 32'b0;

				beq = 1'b0;
				bne = 1'b0;
				blt = 1'b0;
				bge = 1'b0;
			end

			7'b0010011: //Immediate Type Instruction
			begin
				alu_src_from_imem = 1'b1;
				reg_write = 1'b1;
				//3bit-Opcode
				funct3 = ip_instr_from_imem[14:12];	
				//7bit-Functionality
				funct7 = ip_instr_from_imem[31:25];
				mem_read = 1'b0;
				mem_write = 1'b0;
				mem_to_reg = 1'b0;
				if ((funct3 != 3'b001) && (funct3 != 3'b101))
					imem_sign_ext = {{20{ip_instr_from_imem[31]}}, ip_instr_from_imem[31:20]};
				else
					imem_sign_ext = {{20{1'b0}}, {7{1'b0}}, ip_instr_from_imem[24:20]};

				beq = 1'b0;
				bne = 1'b0;
				blt = 1'b0;
				bge = 1'b0;
			end

			7'b0000011: //Load Word
			begin
				alu_src_from_imem = 1'b1;
				reg_write = 1'b1;
				//funct3 = ip_instr_from_imem[14:12];
				funct3 = 3'b000;
				funct7 = 7'b0;
				mem_read = 1'b1;
				mem_write = 1'b0;
				mem_to_reg = 1'b1;
				imem_sign_ext = {{20{ip_instr_from_imem[31]}}, ip_instr_from_imem[31:20]};

				beq = 1'b0;
				bne = 1'b0;
				blt = 1'b0;
				bge = 1'b0;
			end

			7'b0100011: //Store Word
			begin
				alu_src_from_imem = 1'b1;
				reg_write = 1'b0;
				//funct3 = ip_instr_from_imem[14:12];
				funct3 = 3'b000;
				funct7 = 7'b0;
				mem_read = 1'b0;
				mem_write = 1'b1;
				mem_to_reg = 1'bx;
				imem_sign_ext = {{20{ip_instr_from_imem[31]}}, ip_instr_from_imem[31:25], ip_instr_from_imem[11:7]};

				beq = 1'b0;
				bne = 1'b0;
				blt = 1'b0;
				bge = 1'b0;
			end

			7'b1100011: //Controlled Branches
			begin
				alu_src_from_imem = 1'b0;
				reg_write = 1'b0;
				funct3 = 3'b000;
				funct7 = 7'b0100000;
				mem_read = 1'b0;
				mem_write = 1'b0;
				mem_to_reg = 1'bx;
				imem_sign_ext = {{20{ip_instr_from_imem[31]}}, ip_instr_from_imem[7], ip_instr_from_imem[30:25], ip_instr_from_imem[11:8], 1'b0};
				
				case (ip_instr_from_imem[14:12])
					3'b000:
					begin
						beq = 1'b1;
						bne = 1'b0;
						blt = 1'b0;
						bge = 1'b0;
					end

					3'b001:
					begin
						beq = 1'b0;
						bne = 1'b1;
						blt = 1'b0;
						bge = 1'b0;
					end

					3'b100:
					begin
						beq = 1'b0;
						bne = 1'b0;
						blt = 1'b1;
						bge = 1'b0;
					end
					
					3'b101:
					begin
						beq = 1'b0;
						bne = 1'b0;
						blt = 1'b0;
						bge = 1'b1;
					end
				endcase						
			end
		endcase
	end

end
endmodule

BRANCH_CASES/Reg_Imm_Mem_Beq/processor_v1.v
//Verilog Code for single cycle processor

module processor_v1(

//General inputs
input wire clk,
input wire rst,

//Inputs and Outputs from imem 
input wire [31:0] ip_instr_from_imem,
input wire ip_instr_valid,
output reg [31:0] op_instr_addr_from_proc

);

wire [31:0] read_data1;
wire [31:0] read_data2;
wire [31:0] alu_output;
wire [31:0] wb_data;

//wires to and from Decoder Module
wire alu_src_from_imem;
wire [2:0] funct3;
wire [6:0] funct7;
wire op_data_wr;
wire mem_read_en;
wire mem_write_en;
wire mem_to_reg_en;
wire [31:0] imem_sign_ext;
wire beq;
wire bne;
wire blt;
wire bge;

wire [31:0] mem_out;
wire mem_out_valid;

//wire op_instr_addr_from_proc;
wire [31:0] ip_instr_addr_from_pc;

// intermediate signals wrt immediate instr
wire [31:0] read_data_from_mux;

wire [31:0] br_target_addr;
wire [31:0] updated_pc;

reg mux_en_bta;

reg [31:0] next_pc;
reg [31:0] pc;
wire [31:0] pc_out;

integer debug_file;

initial begin
	debug_file = $fopen("Debugging_File_1.txt", "w");
end

always @(posedge clk) begin
	if (rst) begin
		pc <= 0;
	end
end

always @(*) begin
	next_pc = pc + 32'h4;
	op_instr_addr_from_proc = pc_out;
	mux_en_bta = beq & (alu_output == 0);
        //$fwrite(debug_file,"Instr_Addr_fromPC=%h, imem_sign_ext=%h, ALU_Output=%h, Ip_Instr_from_IMEM=%h, Br_Target_Addr=%h, Op_Instr_from_proc=%h, Beq=%b, Mux_EN_BTA=%b\n", ip_instr_addr_from_pc, imem_sign_ext, alu_output, ip_instr_from_imem, br_target_addr, op_instr_addr_from_proc, beq, mux_en_bta);
end

decoder dec_0 (
	.ip_instr_from_imem(ip_instr_from_imem),  
	.funct3(funct3), //control signal for ALU
	.funct7(funct7), //control signal for ALU
	.ip_instr_valid(ip_instr_valid), //instr is valid or not
	.reg_write(op_data_wr), //register wrtie instr or not
	.alu_src_from_imem(alu_src_from_imem), //reading either from reg_file or immediate data
	.mem_read(mem_read_en),
	.mem_write(mem_write_en),
	.mem_to_reg(mem_to_reg_en),
	.imem_sign_ext(imem_sign_ext),
	.beq(beq),
	.bne(bne),
	.blt(blt),
	.bge(bge)
);

adder adder_0 (
	.inp1(pc),
	.inp2(imem_sign_ext),
	.res (br_target_addr)
);	

alu alu_0 (
	.read_data1(read_data1), //read data1 
	.read_data2(read_data_from_mux), //read data either from reg_file or immediate
	.funct3(funct3), 
	.funct7(funct7), 
	.result(alu_output) //final result from ALU
);

dmem dmem_0 (
	.clk(clk),
	.ip_mem_read(mem_read_en),
	.ip_mem_write(mem_write_en),
	.ip_mem_addr(alu_output),
	.ip_mem_data(read_data2),
	.op_mem_out(mem_out),
	.op_mem_data_valid(mem_out_valid)
);

mux_32 mux_32_0 (
	.inp0(read_data2),
	.inp1(imem_sign_ext),
	.sel(alu_src_from_imem),
	.out(read_data_from_mux)
);

mux_32 mux_32_1 (
	.inp0(alu_output),
	.inp1(mem_out),
	.sel(mem_to_reg_en),
	.out(wb_data)
);

mux_32 mux_32_2 (
	.inp0(next_pc),
	.inp1(br_target_addr),
	.sel(mux_en_bta),
	.out(pc_out)
);

regfile regfile_0 (
	.reg_src1(ip_instr_from_imem[19:15]), //reg_source 1
	.reg_src2(ip_instr_from_imem[24:20]), //reg_source 2
	.reg_dest(ip_instr_from_imem[11:7]),  //reg_dest
	.write_back(wb_data), //data to be written
	.clk(clk), 
	.rst(rst), 
	.write_en(op_data_wr), //to write into reg_file if its a reg_write instr
	.read_data1(read_data1), //data from reg_source1
	.read_data2(read_data2) //data from reg_source2
);

endmodule

RTL/SoC.v
//Top Module which instantiate Memory Modules and Processor 

module SoC (
	//General Inputs
	input wire clk,
	input wire rst
);

wire [31:0] instr_addr_from_proc; 


wire [31:0] instr_from_imem;
wire instr_valid_from_imem;

//Instantiation of Processor and IMEM

processor_v1 processor_v1_0 (
	.clk(clk), 
	.rst(rst), 
	.ip_instr_from_imem(instr_from_imem), 
	.ip_instr_valid(instr_valid_from_imem), 
	.op_instr_addr_from_proc(instr_addr_from_proc)
);

imem imem_0 (
.ip_instr_addr_from_proc(instr_addr_from_proc), 
.op_instr_from_imem(instr_from_imem), 
.op_instr_valid(instr_valid_from_imem)
);

endmodule

BRANCH_CASES/004_Branch_tests/tb.v
//Verilog Code for testing the Processor

//TestBench- Inputs and Outputs which you are giving and viewing respectively.
//Also to facilitate instantiation between two or more instants of module
//(Primarly taking and giving values between instanted modules)

`timescale 1ns/1ps

module tb;

reg clk;
reg rst;

//Clock
always #5 clk = ~clk;

//To count number of clocks
integer clock;

//To open the reg file and to dump data into it
integer reg_file_contents;
integer mem_file_contents;
integer i;

initial begin

	//Dumping values into VCD using system_task for plotting signals
	$dumpfile("wave.vcd");

	//Dumping all the top level signal of the test bench- scope:0 
	$dumpvars(0, tb);
	
	//Storing the values from imem file to imem memory
	$readmemh("imem.fill", SoC_0.imem_0.mem);
	$readmemh("dmem.fill", SoC_0.processor_v1_0.dmem_0.mem);
	$readmemh("rf.fill", SoC_0.processor_v1_0.regfile_0.mem);
	
	//Resetting the Values
	clk <= 0;
	rst <= 1;
	clock <= 0;

	//After 5 negedge make reset 0
	@(negedge clk);

	repeat(5) begin 
		@(negedge clk);
	end
	
	rst <= 0;

	//Once the reset is 0, the program will run and by fetching the
	//instruction all 32 bit 0 indicated the end of the program.
	wait(SoC_0.instr_from_imem == 32'b0);
	$display("The program completed in the %d clock cycles", clock);

	////Draining pipeline
	//repeat(5) @(negedge clk);

	//Dump all the content in the registers into the file with dump
	//extenstion
	reg_file_contents=$fopen("rf_values.dump");

	for(i=0; i<32 ; i=i+1) begin
		$fdisplay(reg_file_contents,"Register %d : %h", i, SoC_0.processor_v1_0.regfile_0.mem[i]);
	end
	$fclose(reg_file_contents);

	mem_file_contents=$fopen("dmem_values.dump");

	for(i=0; i<32; i=i+1) begin
		$fdisplay(mem_file_contents,"Memory %d : %h", i, SoC_0.processor_v1_0.dmem_0.mem[i]);
	end
	$fclose(mem_file_contents);

	$finish;
end

always @(posedge clk) begin
	if (rst) begin
		clock <= 0;
	end
	else begin
		clock <= clock + 1;
	end
end

//To avoid infinte loops
initial begin
	#10000
	$display("Test timeout, there should be infinite loop!!! Please check");
	$finish;
end

//Instantiation of SoC

SoC SoC_0 (
	.clk(clk),
	.rst(rst)
);

endmodule

BRANCH_CASES/004_Branch_tests/wave.vcd
$date
	Sun Apr  2 21:07:18 2023
$end
$version
	Icarus Verilog
$end
$timescale
	1ps
$end
$scope module tb $end
$var reg 1 ! clk $end
$var reg 1 " rst $end
$var integer 32 # clock [31:0] $end
$var integer 32 $ i [31:0] $end
$var integer 32 % mem_file_contents [31:0] $end
$var integer 32 & reg_file_contents [31:0] $end
$scope module SoC_0 $end
$var wire 1 ! clk $end
$var wire 1 " rst $end
$var wire 1 ' instr_valid_from_imem $end
$var wire 32 ( instr_from_imem [31:0] $end
$var wire 32 ) instr_addr_from_proc [31:0] $end
$scope module imem_0 $end
$var wire 32 * ip_instr_addr_from_proc [31:0] $end
$var reg 32 + op_instr_from_imem [31:0] $end
$var reg 1 ' op_instr_valid $end
$scope begin imem_block $end
$upscope $end
$upscope $end
$scope module processor_v1_0 $end
$var wire 1 ! clk $end
$var wire 32 , ip_instr_from_imem [31:0] $end
$var wire 1 ' ip_instr_valid $end
$var wire 1 " rst $end
$var wire 32 - wb_data [31:0] $end
$var wire 32 . read_data_from_mux [31:0] $end
$var wire 32 / read_data2 [31:0] $end
$var wire 32 0 read_data1 [31:0] $end
$var wire 32 1 pc_out [31:0] $end
$var wire 1 2 op_data_wr $end
$var wire 1 3 mem_write_en $end
$var wire 1 4 mem_to_reg_en $end
$var wire 1 5 mem_read_en $end
$var wire 1 6 mem_out_valid $end
$var wire 32 7 mem_out [31:0] $end
$var wire 32 8 imem_sign_ext [31:0] $end
$var wire 7 9 funct7 [6:0] $end
$var wire 3 : funct3 [2:0] $end
$var wire 32 ; br_target_addr [31:0] $end
$var wire 1 < bne $end
$var wire 1 = blt $end
$var wire 1 > bge $end
$var wire 1 ? beq $end
$var wire 1 @ alu_src_from_imem $end
$var wire 32 A alu_output [31:0] $end
$var reg 1 B mux_en_bta $end
$var reg 32 C next_pc [31:0] $end
$var reg 32 D op_instr_addr_from_proc [31:0] $end
$var reg 32 E pc [31:0] $end
$var integer 32 F debug_file [31:0] $end
$scope module adder_0 $end
$var wire 32 G inp1 [31:0] $end
$var wire 32 H inp2 [31:0] $end
$var reg 32 I res [31:0] $end
$upscope $end
$scope module alu_0 $end
$var wire 32 J read_data2 [31:0] $end
$var wire 32 K read_data1 [31:0] $end
$var wire 7 L funct7 [6:0] $end
$var wire 3 M funct3 [2:0] $end
$var reg 32 N result [31:0] $end
$scope begin ALU_Block $end
$upscope $end
$upscope $end
$scope module dec_0 $end
$var wire 32 O ip_instr_from_imem [31:0] $end
$var wire 1 ' ip_instr_valid $end
$var reg 1 @ alu_src_from_imem $end
$var reg 1 ? beq $end
$var reg 1 > bge $end
$var reg 1 = blt $end
$var reg 1 < bne $end
$var reg 3 P funct3 [2:0] $end
$var reg 7 Q funct7 [6:0] $end
$var reg 32 R imem_sign_ext [31:0] $end
$var reg 1 5 mem_read $end
$var reg 1 4 mem_to_reg $end
$var reg 1 3 mem_write $end
$var reg 1 2 reg_write $end
$scope begin decoder_block $end
$upscope $end
$upscope $end
$scope module dmem_0 $end
$var wire 1 ! clk $end
$var wire 32 S ip_mem_addr [31:0] $end
$var wire 1 5 ip_mem_read $end
$var wire 1 3 ip_mem_write $end
$var wire 32 T ip_mem_data [31:0] $end
$var reg 1 6 op_mem_data_valid $end
$var reg 32 U op_mem_out [31:0] $end
$scope begin dmem_read_block $end
$upscope $end
$scope begin dmem_write_block $end
$upscope $end
$upscope $end
$scope module mux_32_0 $end
$var wire 32 V inp1 [31:0] $end
$var wire 1 @ sel $end
$var wire 32 W inp0 [31:0] $end
$var reg 32 X out [31:0] $end
$upscope $end
$scope module mux_32_1 $end
$var wire 32 Y inp0 [31:0] $end
$var wire 32 Z inp1 [31:0] $end
$var wire 1 4 sel $end
$var reg 32 [ out [31:0] $end
$upscope $end
$scope module mux_32_2 $end
$var wire 32 \ inp0 [31:0] $end
$var wire 32 ] inp1 [31:0] $end
$var wire 1 B sel $end
$var reg 32 ^ out [31:0] $end
$upscope $end
$scope module regfile_0 $end
$var wire 1 ! clk $end
$var wire 5 _ reg_dest [4:0] $end
$var wire 5 ` reg_src1 [4:0] $end
$var wire 5 a reg_src2 [4:0] $end
$var wire 1 " rst $end
$var wire 32 b write_back [31:0] $end
$var wire 1 2 write_en $end
$var reg 32 c read_data1 [31:0] $end
$var reg 32 d read_data2 [31:0] $end
$scope begin register_file_block $end
$upscope $end
$upscope $end
$upscope $end
$upscope $end
$upscope $end
$enddefinitions $end
#0
$dumpvars
bx d
bx c
bx b
bx a
bx `
bx _
bx ^
bx ]
bx \
bx [
bx Z
bx Y
bx X
bx W
bx V
bx U
bx T
bx S
bx R
bx Q
bx P
bx O
bx N
bx M
bx L
bx K
bx J
bx I
bx H
bx G
b10000000000000000000000000000011 F
bx E
bx D
bx C
xB
bx A
x@
x?
x>
x=
x<
bx ;
bx :
bx 9
bx 8
bx 7
x6
x5
x4
x3
x2
bx 1
bx 0
bx /
bx .
bx -
bx ,
bx +
bx *
bx )
bx (
1'
bx &
bx %
bx $
b0 #
1"
0!
$end
#5000
b11 -
b11 [
b11 b
b11 A
b11 N
b11 S
b11 Y
b10 .
b10 J
b10 X
b10 /
b10 T
b10 W
b10 d
b1 0
b1 K
b1 c
0B
b0 ;
b0 I
b0 ]
b1 `
b10 a
b10 _
0>
0=
0<
0?
b0 8
b0 H
b0 R
b0 V
04
03
05
b0 9
b0 L
b0 Q
b0 :
b0 M
b0 P
0@
12
b1000001000000100110011 (
b1000001000000100110011 +
b1000001000000100110011 ,
b1000001000000100110011 O
b100 )
b100 *
b100 D
b100 1
b100 ^
b100 C
b100 \
b0 E
b0 G
1!
#10000
0!
#15000
b100 -
b100 [
b100 b
b100 A
b100 N
b100 S
b100 Y
b11 .
b11 J
b11 X
b11 /
b11 T
b11 W
b11 d
1!
#20000
0!
#25000
b101 -
b101 [
b101 b
b101 A
b101 N
b101 S
b101 Y
b100 .
b100 J
b100 X
b100 /
b100 T
b100 W
b100 d
1!
#30000
0!
#35000
b110 -
b110 [
b110 b
b110 A
b110 N
b110 S
b110 Y
b101 .
b101 J
b101 X
b101 /
b101 T
b101 W
b101 d
1!
#40000
0!
#45000
b111 -
b111 [
b111 b
b111 A
b111 N
b111 S
b111 Y
b110 .
b110 J
b110 X
b110 /
b110 T
b110 W
b110 d
1!
#50000
0"
0!
#55000
b1000 -
b1000 [
b1000 b
b1000 A
b1000 N
b1000 S
b1000 Y
b111 .
b111 J
b111 X
b111 /
b111 T
b111 W
b111 d
b1 #
1!
#60000
0!
#65000
b1001 -
b1001 [
b1001 b
b1001 A
b1001 N
b1001 S
b1001 Y
b1000 .
b1000 J
b1000 X
b1000 /
b1000 T
b1000 W
b1000 d
b10 #
1!
#70000
0!
#75000
b1010 -
b1010 [
b1010 b
b1010 A
b1010 N
b1010 S
b1010 Y
b1001 .
b1001 J
b1001 X
b1001 /
b1001 T
b1001 W
b1001 d
b11 #
1!
#80000
0!
#85000
b1011 -
b1011 [
b1011 b
b1011 A
b1011 N
b1011 S
b1011 Y
b1010 .
b1010 J
b1010 X
b1010 /
b1010 T
b1010 W
b1010 d
b100 #
1!
#90000
0!
#95000
b1100 -
b1100 [
b1100 b
b1100 A
b1100 N
b1100 S
b1100 Y
b1011 .
b1011 J
b1011 X
b1011 /
b1011 T
b1011 W
b1011 d
b101 #
1!
#100000
0!
#105000
b1101 -
b1101 [
b1101 b
b1101 A
b1101 N
b1101 S
b1101 Y
b1100 .
b1100 J
b1100 X
b1100 /
b1100 T
b1100 W
b1100 d
b110 #
1!
#110000
0!
#115000
b1110 -
b1110 [
b1110 b
b1110 A
b1110 N
b1110 S
b1110 Y
b1101 .
b1101 J
b1101 X
b1101 /
b1101 T
b1101 W
b1101 d
b111 #
1!
#120000
0!
#125000
b1111 -
b1111 [
b1111 b
b1111 A
b1111 N
b1111 S
b1111 Y
b1110 .
b1110 J
b1110 X
b1110 /
b1110 T
b1110 W
b1110 d
b1000 #
1!
#130000
0!
#135000
b10000 -
b10000 [
b10000 b
b10000 A
b10000 N
b10000 S
b10000 Y
b1111 .
b1111 J
b1111 X
b1111 /
b1111 T
b1111 W
b1111 d
b1001 #
1!
#140000
0!
#145000
b10001 -
b10001 [
b10001 b
b10001 A
b10001 N
b10001 S
b10001 Y
b10000 .
b10000 J
b10000 X
b10000 /
b10000 T
b10000 W
b10000 d
b1010 #
1!
#150000
0!
#155000
b10010 -
b10010 [
b10010 b
b10010 A
b10010 N
b10010 S
b10010 Y
b10001 .
b10001 J
b10001 X
b10001 /
b10001 T
b10001 W
b10001 d
b1011 #
1!
#160000
0!
#165000
b10011 -
b10011 [
b10011 b
b10011 A
b10011 N
b10011 S
b10011 Y
b10010 .
b10010 J
b10010 X
b10010 /
b10010 T
b10010 W
b10010 d
b1100 #
1!
#170000
0!
#175000
b10100 -
b10100 [
b10100 b
b10100 A
b10100 N
b10100 S
b10100 Y
b10011 .
b10011 J
b10011 X
b10011 /
b10011 T
b10011 W
b10011 d
b1101 #
1!
#180000
0!
#185000
b10101 -
b10101 [
b10101 b
b10101 A
b10101 N
b10101 S
b10101 Y
b10100 .
b10100 J
b10100 X
b10100 /
b10100 T
b10100 W
b10100 d
b1110 #
1!
#190000
0!
#195000
b10110 -
b10110 [
b10110 b
b10110 A
b10110 N
b10110 S
b10110 Y
b10101 .
b10101 J
b10101 X
b10101 /
b10101 T
b10101 W
b10101 d
b1111 #
1!
#200000
0!
#205000
b10111 -
b10111 [
b10111 b
b10111 A
b10111 N
b10111 S
b10111 Y
b10110 .
b10110 J
b10110 X
b10110 /
b10110 T
b10110 W
b10110 d
b10000 #
1!
#210000
0!
#215000
b11000 -
b11000 [
b11000 b
b11000 A
b11000 N
b11000 S
b11000 Y
b10111 .
b10111 J
b10111 X
b10111 /
b10111 T
b10111 W
b10111 d
b10001 #
1!
#220000
0!
#225000
b11001 -
b11001 [
b11001 b
b11001 A
b11001 N
b11001 S
b11001 Y
b11000 .
b11000 J
b11000 X
b11000 /
b11000 T
b11000 W
b11000 d
b10010 #
1!
#230000
0!
#235000
b11010 -
b11010 [
b11010 b
b11010 A
b11010 N
b11010 S
b11010 Y
b11001 .
b11001 J
b11001 X
b11001 /
b11001 T
b11001 W
b11001 d
b10011 #
1!
#240000
0!
#245000
b11011 -
b11011 [
b11011 b
b11011 A
b11011 N
b11011 S
b11011 Y
b11010 .
b11010 J
b11010 X
b11010 /
b11010 T
b11010 W
b11010 d
b10100 #
1!
#250000
0!
#255000
b11100 -
b11100 [
b11100 b
b11100 A
b11100 N
b11100 S
b11100 Y
b11011 .
b11011 J
b11011 X
b11011 /
b11011 T
b11011 W
b11011 d
b10101 #
1!
#260000
0!
#265000
b11101 -
b11101 [
b11101 b
b11101 A
b11101 N
b11101 S
b11101 Y
b11100 .
b11100 J
b11100 X
b11100 /
b11100 T
b11100 W
b11100 d
b10110 #
1!
#270000
0!
#275000
b11110 -
b11110 [
b11110 b
b11110 A
b11110 N
b11110 S
b11110 Y
b11101 .
b11101 J
b11101 X
b11101 /
b11101 T
b11101 W
b11101 d
b10111 #
1!
#280000
0!
#285000
b11111 -
b11111 [
b11111 b
b11111 A
b11111 N
b11111 S
b11111 Y
b11110 .
b11110 J
b11110 X
b11110 /
b11110 T
b11110 W
b11110 d
b11000 #
1!
#290000
0!
#295000
b100000 -
b100000 [
b100000 b
b100000 A
b100000 N
b100000 S
b100000 Y
b11111 .
b11111 J
b11111 X
b11111 /
b11111 T
b11111 W
b11111 d
b11001 #
1!
#300000
0!
#305000
b100001 -
b100001 [
b100001 b
b100001 A
b100001 N
b100001 S
b100001 Y
b100000 .
b100000 J
b100000 X
b100000 /
b100000 T
b100000 W
b100000 d
b11010 #
1!
#310000
0!
#315000
b100010 -
b100010 [
b100010 b
b100010 A
b100010 N
b100010 S
b100010 Y
b100001 .
b100001 J
b100001 X
b100001 /
b100001 T
b100001 W
b100001 d
b11011 #
1!
#320000
0!
#325000
b100011 -
b100011 [
b100011 b
b100011 A
b100011 N
b100011 S
b100011 Y
b100010 .
b100010 J
b100010 X
b100010 /
b100010 T
b100010 W
b100010 d
b11100 #
1!
#330000
0!
#335000
b100100 -
b100100 [
b100100 b
b100100 A
b100100 N
b100100 S
b100100 Y
b100011 .
b100011 J
b100011 X
b100011 /
b100011 T
b100011 W
b100011 d
b11101 #
1!
#340000
0!
#345000
b100101 -
b100101 [
b100101 b
b100101 A
b100101 N
b100101 S
b100101 Y
b100100 .
b100100 J
b100100 X
b100100 /
b100100 T
b100100 W
b100100 d
b11110 #
1!
#350000
0!
#355000
b100110 -
b100110 [
b100110 b
b100110 A
b100110 N
b100110 S
b100110 Y
b100101 .
b100101 J
b100101 X
b100101 /
b100101 T
b100101 W
b100101 d
b11111 #
1!
#360000
0!
#365000
b100111 -
b100111 [
b100111 b
b100111 A
b100111 N
b100111 S
b100111 Y
b100110 .
b100110 J
b100110 X
b100110 /
b100110 T
b100110 W
b100110 d
b100000 #
1!
#370000
0!
#375000
b101000 -
b101000 [
b101000 b
b101000 A
b101000 N
b101000 S
b101000 Y
b100111 .
b100111 J
b100111 X
b100111 /
b100111 T
b100111 W
b100111 d
b100001 #
1!
#380000
0!
#385000
b101001 -
b101001 [
b101001 b
b101001 A
b101001 N
b101001 S
b101001 Y
b101000 .
b101000 J
b101000 X
b101000 /
b101000 T
b101000 W
b101000 d
b100010 #
1!
#390000
0!
#395000
b101010 -
b101010 [
b101010 b
b101010 A
b101010 N
b101010 S
b101010 Y
b101001 .
b101001 J
b101001 X
b101001 /
b101001 T
b101001 W
b101001 d
b100011 #
1!
#400000
0!
#405000
b101011 -
b101011 [
b101011 b
b101011 A
b101011 N
b101011 S
b101011 Y
b101010 .
b101010 J
b101010 X
b101010 /
b101010 T
b101010 W
b101010 d
b100100 #
1!
#410000
0!
#415000
b101100 -
b101100 [
b101100 b
b101100 A
b101100 N
b101100 S
b101100 Y
b101011 .
b101011 J
b101011 X
b101011 /
b101011 T
b101011 W
b101011 d
b100101 #
1!
#420000
0!
#425000
b101101 -
b101101 [
b101101 b
b101101 A
b101101 N
b101101 S
b101101 Y
b101100 .
b101100 J
b101100 X
b101100 /
b101100 T
b101100 W
b101100 d
b100110 #
1!
#430000
0!
#435000
b101110 -
b101110 [
b101110 b
b101110 A
b101110 N
b101110 S
b101110 Y
b101101 .
b101101 J
b101101 X
b101101 /
b101101 T
b101101 W
b101101 d
b100111 #
1!
#440000
0!
#445000
b101111 -
b101111 [
b101111 b
b101111 A
b101111 N
b101111 S
b101111 Y
b101110 .
b101110 J
b101110 X
b101110 /
b101110 T
b101110 W
b101110 d
b101000 #
1!
#450000
0!
#455000
b110000 -
b110000 [
b110000 b
b110000 A
b110000 N
b110000 S
b110000 Y
b101111 .
b101111 J
b101111 X
b101111 /
b101111 T
b101111 W
b101111 d
b101001 #
1!
#460000
0!
#465000
b110001 -
b110001 [
b110001 b
b110001 A
b110001 N
b110001 S
b110001 Y
b110000 .
b110000 J
b110000 X
b110000 /
b110000 T
b110000 W
b110000 d
b101010 #
1!
#470000
0!
#475000
b110010 -
b110010 [
b110010 b
b110010 A
b110010 N
b110010 S
b110010 Y
b110001 .
b110001 J
b110001 X
b110001 /
b110001 T
b110001 W
b110001 d
b101011 #
1!
#480000
0!
#485000
b110011 -
b110011 [
b110011 b
b110011 A
b110011 N
b110011 S
b110011 Y
b110010 .
b110010 J
b110010 X
b110010 /
b110010 T
b110010 W
b110010 d
b101100 #
1!
#490000
0!
#495000
b110100 -
b110100 [
b110100 b
b110100 A
b110100 N
b110100 S
b110100 Y
b110011 .
b110011 J
b110011 X
b110011 /
b110011 T
b110011 W
b110011 d
b101101 #
1!
#500000
0!
#505000
b110101 -
b110101 [
b110101 b
b110101 A
b110101 N
b110101 S
b110101 Y
b110100 .
b110100 J
b110100 X
b110100 /
b110100 T
b110100 W
b110100 d
b101110 #
1!
#510000
0!
#515000
b110110 -
b110110 [
b110110 b
b110110 A
b110110 N
b110110 S
b110110 Y
b110101 .
b110101 J
b110101 X
b110101 /
b110101 T
b110101 W
b110101 d
b101111 #
1!
#520000
0!
