RTL/MEM/imem.v
//Verilog code for Instruction Memory

module imem(

input wire [31:0] ip_instr_addr_from_proc,
output reg [31:0] op_instr_from_imem,
output reg op_instr_valid
);

//Memory to hold the instructions

reg [31:0] mem[31:0];

//Reading instruction is harmless and it doesn't need any control signal
always @(*) begin: imem_block
	op_instr_from_imem= mem[ip_instr_addr_from_proc [31:2]];
	op_instr_valid =1'b1;
end

endmodule

RTL/CORES/Reg_Imm_Mem_Beq_v2/pc.v
//Verilog Code for Program Counter

module pc(

input wire clk,
input wire rst,
output reg [31:0] op_instr_addr
);

//reg rst_tracker;
reg [31:0] pc;
reg [31:0] next_pc;

always @(posedge clk) begin: PC_Block
	//rst_tracker <= rst;
	
	if (rst) begin
		pc <= 0;
	end
	else begin
		pc <= next_pc;
	end
end

always @(*) begin
	op_instr_addr = pc;	
	next_pc = pc + 32'h4;
end

endmodule

RTL/CORES/Reg_Imm_Mem/register_file.v
// Feb 10, 2023
// Verilog Code for Register File

module regfile( 

input wire [4:0] reg_src1,
input wire [4:0] reg_src2,
input wire [4:0] reg_dest,
input wire [31:0] write_back,
input wire clk,
input wire rst,
input wire write_en,
output reg [31:0] read_data1,
output reg [31:0] read_data2
);

//32 Registers of each 32 bit
reg [31:0] mem[31:0];

//Reading from register file is harmless so no need of the control signal

always @(*) begin
	read_data1=mem[reg_src1];
	read_data2=mem[reg_src2];
end

always @(posedge clk ) begin: register_file_block
	if (write_en) begin
		mem[reg_dest] <= write_back;
	end
	
	//0th Register always holds value 0's
	mem[0] <= 'b0;
end


//always @(posedge clk or posedge rst) begin: register_file_block
//	if (rst) begin
//		mem <= 'b0;
//	end
//	else begin
//	 	if (write_en) begin
//			mem[reg_dst] <= write_back;
//		end
//	end
//	//0th Register always holds value 0's
//	mem[0] <= 'b0;
//end

endmodule

RTL/CORES/Reg_Imm_Mem_Beq_v2/mux_32.v
//Verilog Module for 32 bit Mux Logic


module mux_32(
input wire [31:0] inp0,
input wire [31:0] inp1,
input wire sel,
output reg [31:0] out
);

always @(*) begin
	if (sel) 
		out = inp1;
	else
		out = inp0;
end
endmodule

RTL/MEM/dmem.v
//Verilog Code for Data Memory

module dmem (
	input wire clk,
	input wire ip_mem_read,
	input wire ip_mem_write,

	input wire [31:0] ip_mem_addr,
	input wire [31:0] ip_mem_data,

	output reg [31:0] op_mem_out,
	output reg  op_mem_data_valid
);

//Actual Data Memory
reg [31:0] mem[31:0];

always @(*) begin : dmem_read_block
	if (ip_mem_read) begin
		op_mem_out = mem[ip_mem_addr[31:2]];
		op_mem_data_valid = 1'b1;
	end
end

always @(posedge clk) begin : dmem_write_block
	if (ip_mem_write) begin
		mem[ip_mem_addr[31:2]] <= ip_mem_data;
	end
end

endmodule

BRANCH_CASES/Reg_Imm_Mem_Beq/alu.v
//Verilog Code for ALU

module alu(

input wire [31:0] read_data1,
input wire [31:0] read_data2,
input wire [2:0] funct3,
input wire [6:0] funct7,
output reg [31:0] result
);

always @(*) begin: ALU_Block
	case (funct3)
		3'b000 :
		begin	
			if (funct7 != 7'b0100000)
				result = read_data1 + read_data2;   //ADD
			else
				result = read_data1 - read_data2;   //SUB 
		end
		3'b001 : result = read_data1 << read_data2;  //Shift Logical Left
		3'b010 : 				     //Set Less Than		
			if (read_data1 < read_data2) begin
				result = 1;
			end
			else begin 
				result = 0;
			end
		3'b011 :				     //S.L.T.Unsigned
 			if (read_data1 < read_data2) begin
				result = 1;
			end
			else begin 
				result = 0;
			end
		3'b100 : result = (read_data1 ^ read_data2); //XOR
		3'b101 :
		begin
			if (funct7 != 7'b0100000) 	
				result = read_data1 >> read_data2;  //Shift Right Logical
			else
				result = read_data1 >>> read_data2; //Shift Right Arithmetic
		end	
		3'b110 : result = read_data1 | read_data2;  //OR
		3'b111 : result = read_data1 & read_data2;  //AND
		default: result = 'b0;
	endcase
	
end
endmodule

RTL/CORES/Reg_Imm_Mem/decoder.v
//Verilog code for the Decoder- to generate control signals.

module decoder(

input wire [31:0] ip_instr_from_imem,
input wire ip_instr_valid,
output reg reg_write,
output reg [2:0] funct3,
output reg [6:0] funct7,
output reg alu_src_from_imem,
output reg mem_read,
output reg mem_write,
output reg mem_to_reg,
output reg [31:0] imem_sign_ext
);

always @(*) begin:decoder_block
	if (ip_instr_valid) begin
		case (ip_instr_from_imem[6:0]) 
			7'b0110011: //R-type Instruction 
			begin
				reg_write=1'b1;
			        alu_src_from_imem = 1'b0;	
				//3bit-Opcode
				funct3=ip_instr_from_imem[14:12];
				//7bit-Functionality
				funct7=ip_instr_from_imem[31:25];
				mem_read = 1'b0;
				mem_write = 1'b0;
				mem_to_reg = 1'b0;
			 	imem_sign_ext = 32'b0;
			end

			7'b0010011: //Immediate Type Instruction
			begin
				alu_src_from_imem = 1'b1;
				reg_write = 1'b1;
				//3bit-Opcode
				funct3 = ip_instr_from_imem[14:12];	
				//7bit-Functionality
				funct7 = ip_instr_from_imem[31:25];
				mem_read = 1'b0;
				mem_write = 1'b0;
				mem_to_reg = 1'b0;
				if ((funct3 != 3'b001) && (funct3 != 3'b101))
					imem_sign_ext = {{20{ip_instr_from_imem[31]}}, ip_instr_from_imem[31:20]};
				else
					imem_sign_ext = {{20{1'b0}}, {7{1'b0}}, ip_instr_from_imem[24:20]};
			end

			7'b0000011: //Load Word
			begin
				alu_src_from_imem = 1'b1;
				reg_write = 1'b1;
				//funct3 = ip_instr_from_imem[14:12];
				funct3 = 3'b000;
				funct7 = 7'b0;
				mem_read = 1'b1;
				mem_write = 1'b0;
				mem_to_reg = 1'b1;
				imem_sign_ext = {{20{ip_instr_from_imem[31]}}, ip_instr_from_imem[31:20]};
			end

			7'b0100011: //Store Word
			begin
				alu_src_from_imem = 1'b1;
				reg_write = 1'b0;
				//funct3 = ip_instr_from_imem[14:12];
				funct3 = 3'b000;
				funct7 = 7'b0;
				mem_read = 1'b0;
				mem_write = 1'b1;
				mem_to_reg = 1'bx;
				imem_sign_ext = {{20{ip_instr_from_imem[31]}}, ip_instr_from_imem[31:25], ip_instr_from_imem[11:7]};
			end

		endcase
	end

end
endmodule

RTL/CORES/Reg_Imm_Mem/processor_v1.v
//Verilog Code for single cycle processor

module processor_v1(

//General inputs
input wire clk,
input wire rst,

//Inputs and Outputs from imem 
input wire [31:0] ip_instr_from_imem,
input wire ip_instr_valid,
output reg [31:0] op_instr_addr_from_proc

);

wire [31:0] read_data1;
wire [31:0] read_data2;
wire [31:0] alu_output;
wire [31:0] wb_data;

//wires to and from Decoder Module
wire alu_src_from_imem;
wire [2:0] funct3;
wire [6:0] funct7;
wire op_data_wr;
wire mem_read_en;
wire mem_write_en;
wire mem_to_reg_en;
wire [31:0] imem_sign_ext;

wire [31:0] mem_out;
wire mem_out_valid;

//wire op_instr_addr_from_proc;
wire [31:0] ip_instr_addr_from_pc;

// intermediate signals wrt immediate instr
wire [31:0] read_data_from_mux;

always @(*) begin
	op_instr_addr_from_proc = ip_instr_addr_from_pc;
end

decoder dec_0 (
	.ip_instr_from_imem(ip_instr_from_imem),  
	.funct3(funct3), //control signal for ALU
	.funct7(funct7), //control signal for ALU
	.ip_instr_valid(ip_instr_valid), //instr is valid or not
	.reg_write(op_data_wr), //register wrtie instr or not
	.alu_src_from_imem(alu_src_from_imem), //reading either from reg_file or immediate data
	.mem_read(mem_read_en),
	.mem_write(mem_write_en),
	.mem_to_reg(mem_to_reg_en),
	.imem_sign_ext(imem_sign_ext)
);

alu alu_0 (
	.read_data1(read_data1), //read data1 
	.read_data2(read_data_from_mux), //read data either from reg_file or immediate
	.funct3(funct3), 
	.funct7(funct7), 
	.result(alu_output) //final result from ALU
);

dmem dmem_0 (
	.clk(clk),
	.ip_mem_read(mem_read_en),
	.ip_mem_write(mem_write_en),
	.ip_mem_addr(alu_output),
	.ip_mem_data(read_data2),
	.op_mem_out(mem_out),
	.op_mem_data_valid(mem_out_valid)
);

mux_32 mux_32_0 (
	.inp0(read_data2),
	.inp1(imem_sign_ext),
	.sel(alu_src_from_imem),
	.out(read_data_from_mux)
);

mux_32 mux_32_1 (
	.inp0(alu_output),
	.inp1(mem_out),
	.sel(mem_to_reg_en),
	.out(wb_data)
);

regfile regfile_0 (
	.reg_src1(ip_instr_from_imem[19:15]), //reg_source 1
	.reg_src2(ip_instr_from_imem[24:20]), //reg_source 2
	.reg_dest(ip_instr_from_imem[11:7]),  //reg_dest
	.write_back(wb_data), //data to be written
	.clk(clk), 
	.rst(rst), 
	.write_en(op_data_wr), //to write into reg_file if its a reg_write instr
	.read_data1(read_data1), //data from reg_source1
	.read_data2(read_data2) //data from reg_source2
);

pc pc_0 (
	.clk(clk), 
	.rst(rst), 
	.op_instr_addr(ip_instr_addr_from_pc)
);


endmodule

RTL/SoC.v
//Top Module which instantiate Memory Modules and Processor 

module SoC (
	//General Inputs
	input wire clk,
	input wire rst
);

wire [31:0] instr_addr_from_proc; 


wire [31:0] instr_from_imem;
wire instr_valid_from_imem;

//Instantiation of Processor and IMEM

processor_v1 processor_v1_0 (
	.clk(clk), 
	.rst(rst), 
	.ip_instr_from_imem(instr_from_imem), 
	.ip_instr_valid(instr_valid_from_imem), 
	.op_instr_addr_from_proc(instr_addr_from_proc)
);

imem imem_0 (
.ip_instr_addr_from_proc(instr_addr_from_proc), 
.op_instr_from_imem(instr_from_imem), 
.op_instr_valid(instr_valid_from_imem)
);

endmodule

TESTS/003_MemType_tests/tb.v
//Verilog Code for testing the Processor

//TestBench- Inputs and Outputs which you are giving and viewing respectively.
//Also to facilitate instantiation between two or more instants of module
//(Primarly taking and giving values between instanted modules)

`timescale 1ns/1ps

module tb;

reg clk;
reg rst;

//Clock
always #5 clk = ~clk;

//To count number of clocks
integer clock;

//To open the reg file and to dump data into it
integer reg_file_contents;
integer mem_file_contents;
integer i;

initial begin

	//Dumping values into VCD using system_task for plotting signals
	$dumpfile("wave.vcd");

	//Dumping all the top level signal of the test bench- scope:0 
	$dumpvars(0, tb);
	
	//Storing the values from imem file to imem memory
	$readmemh("imem.fill", SoC_0.imem_0.mem);
	$readmemh("dmem.fill", SoC_0.processor_v1_0.dmem_0.mem);
	$readmemh("rf.fill", SoC_0.processor_v1_0.regfile_0.mem);
	
	//Resetting the Values
	clk <= 0;
	rst <= 1;
	clock <= 0;

	//After 5 negedge make reset 0
	@(negedge clk);

	repeat(5) begin 
		@(negedge clk);
	end
	
	rst <= 0;

	//Once the reset is 0, the program will run and by fetching the
	//instruction all 32 bit 0 indicated the end of the program.
	wait(SoC_0.instr_from_imem == 32'b0);
	$display("The program completed in the %d clock cycles", clock);

	////Draining pipeline
	//repeat(5) @(negedge clk);

	//Dump all the content in the registers into the file with dump
	//extenstion
	reg_file_contents=$fopen("rf_values.dump");

	for(i=0; i<32 ; i=i+1) begin
		$fdisplay(reg_file_contents,"Register %d : %h", i, SoC_0.processor_v1_0.regfile_0.mem[i]);
	end
	$fclose(reg_file_contents);

	mem_file_contents=$fopen("dmem_values.dump");

	for(i=0; i<32; i=i+1) begin
		$fdisplay(mem_file_contents,"Memory %d : %h", i, SoC_0.processor_v1_0.dmem_0.mem[i]);
	end
	$fclose(mem_file_contents);

	$finish;
end

always @(posedge clk) begin
	if (rst) begin
		clock <= 0;
	end
	else begin
		clock <= clock + 1;
	end
end

//To avoid infinte loops
initial begin
	#1000
	$display("Test timeout, there should be infinite loop!!! Please check");
	$finish;
end

//Instantiation of SoC

SoC SoC_0 (
	.clk(clk),
	.rst(rst)
);

endmodule

TESTS/003_MemType_tests/wave.vcd
$date
	Wed Mar 15 16:58:16 2023
$end
$version
	Icarus Verilog
$end
$timescale
	1ps
$end
$scope module tb $end
$var reg 1 ! clk $end
$var reg 1 " rst $end
$var integer 32 # clock [31:0] $end
$var integer 32 $ i [31:0] $end
$var integer 32 % mem_file_contents [31:0] $end
$var integer 32 & reg_file_contents [31:0] $end
$scope module SoC_0 $end
$var wire 1 ! clk $end
$var wire 1 " rst $end
$var wire 1 ' instr_valid_from_imem $end
$var wire 32 ( instr_from_imem [31:0] $end
$var wire 32 ) instr_addr_from_proc [31:0] $end
$scope module imem_0 $end
$var wire 32 * ip_instr_addr_from_proc [31:0] $end
$var reg 32 + op_instr_from_imem [31:0] $end
$var reg 1 ' op_instr_valid $end
$scope begin imem_block $end
$upscope $end
$upscope $end
$scope module processor_v1_0 $end
$var wire 1 ! clk $end
$var wire 32 , ip_instr_from_imem [31:0] $end
$var wire 1 ' ip_instr_valid $end
$var wire 1 " rst $end
$var wire 32 - wb_data [31:0] $end
$var wire 32 . read_data_from_mux [31:0] $end
$var wire 32 / read_data2 [31:0] $end
$var wire 32 0 read_data1 [31:0] $end
$var wire 1 1 op_data_wr $end
$var wire 1 2 mem_write_en $end
$var wire 1 3 mem_to_reg_en $end
$var wire 1 4 mem_read_en $end
$var wire 1 5 mem_out_valid $end
$var wire 32 6 mem_out [31:0] $end
$var wire 32 7 ip_instr_addr_from_pc [31:0] $end
$var wire 32 8 imem_sign_ext [31:0] $end
$var wire 7 9 funct7 [6:0] $end
$var wire 3 : funct3 [2:0] $end
$var wire 1 ; alu_src_from_imem $end
$var wire 32 < alu_output [31:0] $end
$var reg 32 = op_instr_addr_from_proc [31:0] $end
$scope module alu_0 $end
$var wire 32 > read_data2 [31:0] $end
$var wire 32 ? read_data1 [31:0] $end
$var wire 7 @ funct7 [6:0] $end
$var wire 3 A funct3 [2:0] $end
$var reg 32 B result [31:0] $end
$scope begin ALU_Block $end
$upscope $end
$upscope $end
$scope module dec_0 $end
$var wire 32 C ip_instr_from_imem [31:0] $end
$var wire 1 ' ip_instr_valid $end
$var reg 1 ; alu_src_from_imem $end
$var reg 3 D funct3 [2:0] $end
$var reg 7 E funct7 [6:0] $end
$var reg 32 F imem_sign_ext [31:0] $end
$var reg 1 4 mem_read $end
$var reg 1 3 mem_to_reg $end
$var reg 1 2 mem_write $end
$var reg 1 1 reg_write $end
$scope begin decoder_block $end
$upscope $end
$upscope $end
$scope module dmem_0 $end
$var wire 1 ! clk $end
$var wire 32 G ip_mem_addr [31:0] $end
$var wire 1 4 ip_mem_read $end
$var wire 1 2 ip_mem_write $end
$var wire 32 H ip_mem_data [31:0] $end
$var reg 1 5 op_mem_data_valid $end
$var reg 32 I op_mem_out [31:0] $end
$scope begin dmem_read_block $end
$upscope $end
$scope begin dmem_write_block $end
$upscope $end
$upscope $end
$scope module mux_32_0 $end
$var wire 32 J inp1 [31:0] $end
$var wire 1 ; sel $end
$var wire 32 K inp0 [31:0] $end
$var reg 32 L out [31:0] $end
$upscope $end
$scope module mux_32_1 $end
$var wire 32 M inp0 [31:0] $end
$var wire 32 N inp1 [31:0] $end
$var wire 1 3 sel $end
$var reg 32 O out [31:0] $end
$upscope $end
$scope module pc_0 $end
$var wire 1 ! clk $end
$var wire 1 " rst $end
$var reg 32 P next_pc [31:0] $end
$var reg 32 Q op_instr_addr [31:0] $end
$var reg 32 R pc [31:0] $end
$scope begin PC_Block $end
$upscope $end
$upscope $end
$scope module regfile_0 $end
$var wire 1 ! clk $end
$var wire 5 S reg_dest [4:0] $end
$var wire 5 T reg_src1 [4:0] $end
$var wire 5 U reg_src2 [4:0] $end
$var wire 1 " rst $end
$var wire 32 V write_back [31:0] $end
$var wire 1 1 write_en $end
$var reg 32 W read_data1 [31:0] $end
$var reg 32 X read_data2 [31:0] $end
$scope begin register_file_block $end
$upscope $end
$upscope $end
$upscope $end
$upscope $end
$upscope $end
$enddefinitions $end
#0
$dumpvars
bx X
bx W
bx V
bx U
bx T
bx S
bx R
bx Q
bx P
bx O
bx N
bx M
bx L
bx K
bx J
bx I
bx H
bx G
bx F
bx E
bx D
bx C
bx B
bx A
bx @
bx ?
bx >
bx =
bx <
x;
bx :
bx 9
bx 8
bx 7
bx 6
x5
x4
x3
x2
x1
bx 0
bx /
bx .
bx -
bx ,
bx +
bx *
bx )
bx (
1'
bx &
bx %
bx $
b0 #
1"
0!
$end
#5000
b110110 -
b110110 O
b110110 V
b110110 <
b110110 B
b110110 G
b110110 M
b101100 .
b101100 >
b101100 L
b101100 /
b101100 H
b101100 K
b101100 X
b1010 0
b1010 ?
b1010 W
b100 T
b1000 U
b11 S
b0 8
b0 F
b0 J
03
02
04
b0 9
b0 @
b0 E
b0 :
b0 A
b0 D
0;
11
b100000100000000110110011 (
b100000100000000110110011 +
b100000100000000110110011 ,
b100000100000000110110011 C
b0 )
b0 *
b0 =
b100 P
b0 7
b0 Q
b0 R
1!
#10000
0!
#15000
1!
#20000
0!
#25000
1!
#30000
0!
#35000
1!
#40000
0!
#45000
1!
#50000
0"
0!
#55000
b11 -
b11 O
b11 V
b10 .
b10 >
b10 L
b11 <
b11 B
b11 G
b11 M
b10 /
b10 H
b10 K
b10 X
b1 0
b1 ?
b1 W
b1 T
b10 U
b10 S
b1000001000000100110011 (
b1000001000000100110011 +
b1000001000000100110011 ,
b1000001000000100110011 C
b100 )
b100 *
b100 =
b1000 P
b100 7
b100 Q
b100 R
b1 #
1!
#60000
0!
#65000
b11 0
b11 ?
b11 W
b10 T
b11 U
b1000 S
b111001 -
b111001 O
b111001 V
b1100010000010000110011 (
b1100010000010000110011 +
b1100010000010000110011 ,
b1100010000010000110011 C
b111001 <
b111001 B
b111001 G
b111001 M
b1000 )
b1000 *
b1000 =
b110110 .
b110110 >
b110110 L
b1100 P
b1000 7
b1000 Q
b110110 /
b110110 H
b110110 K
b110110 X
b1000 R
b10 #
1!
#70000
0!
#75000
b110 .
b110 >
b110 L
b1111000000000001000000 -
b1111000000000001000000 O
b1111000000000001000000 V
b110 /
b110 H
b110 K
b110 X
b1111000000000001 0
b1111000000000001 ?
b1111000000000001 W
b1111000000000001000000 <
b1111000000000001000000 B
b1111000000000001000000 G
b1111000000000001000000 M
b1011 T
b1100 U
b1010 S
b1 :
b1 A
b1 D
b110001011001010100110011 (
b110001011001010100110011 +
b110001011001010100110011 ,
b110001011001010100110011 C
b1100 )
b1100 *
b1100 =
b10000 P
b1100 7
b1100 Q
b1100 R
b11 #
1!
#80000
0!
#85000
b1000000000000001100000 -
b1000000000000001100000 O
b1000000000000001100000 V
b101 .
b101 >
b101 L
b1000000000000001100000 <
b1000000000000001100000 B
b1000000000000001100000 G
b1000000000000001100000 M
b101 /
b101 H
b101 K
b101 X
b10000000000000011 0
b10000000000000011 ?
b10000000000000011 W
b1101 T
b1110 U
b1111 S
b111001101001011110110011 (
b111001101001011110110011 +
b111001101001011110110011 ,
b111001101001011110110011 C
b10000 )
b10000 *
b10000 =
b10100 P
b10000 7
b10000 Q
b10000 R
b100 #
1!
#90000
0!
#95000
b10000000000011100 .
b10000000000011100 >
b10000000000011100 L
b1 -
b1 O
b1 V
b10000000000011100 /
b10000000000011100 H
b10000000000011100 K
b10000000000011100 X
b10000000000001100 0
b10000000000001100 ?
b10000000000001100 W
b1 <
b1 B
b1 G
b1 M
b10000 T
b10001 U
b10010 S
b10 :
b10 A
b10 D
b1000110000010100100110011 (
b1000110000010100100110011 +
b1000110000010100100110011 ,
b1000110000010100100110011 C
b10100 )
b10100 *
b10100 =
b11000 P
b10100 7
b10100 Q
b10100 R
b101 #
1!
#100000
0!
#105000
b10001000100010001000100010001 .
b10001000100010001000100010001 >
b10001000100010001000100010001 L
b10001000100010001000100010001 -
b10001000100010001000100010001 O
b10001000100010001000100010001 V
b10001000100010001000100010001 /
b10001000100010001000100010001 H
b10001000100010001000100010001 K
b10001000100010001000100010001 X
b0 0
b0 ?
b0 W
b10001000100010001000100010001 <
b10001000100010001000100010001 B
b10001000100010001000100010001 G
b10001000100010001000100010001 M
b10100 T
b10011 U
b10101 S
b100 :
b100 A
b100 D
b1001110100100101010110011 (
b1001110100100101010110011 +
b1001110100100101010110011 ,
b1001110100100101010110011 C
b11000 )
b11000 *
b11000 =
b11100 P
b11000 7
b11000 Q
b11000 R
b110 #
1!
#110000
0!
#115000
b10001000100010001000100010011 -
b10001000100010001000100010011 O
b10001000100010001000100010011 V
b10001000100010001000100010011 <
b10001000100010001000100010011 B
b10001000100010001000100010011 G
b10001000100010001000100010011 M
b10 .
b10 >
b10 L
b10 /
b10 H
b10 K
b10 X
b10001000100010001000100010001 0
b10001000100010001000100010001 ?
b10001000100010001000100010001 W
b10101 T
b10110 U
b10111 S
b110 :
b110 A
b110 D
b1011010101110101110110011 (
b1011010101110101110110011 +
b1011010101110101110110011 ,
b1011010101110101110110011 C
b11100 )
b11100 *
b11100 =
b100000 P
b11100 7
b11100 Q
b11100 R
b111 #
1!
#120000
0!
#125000
b1010 .
b1010 >
b1010 L
b10 -
b10 O
b10 V
b1010 /
b1010 H
b1010 K
b1010 X
b10001000100010001000100010011 0
b10001000100010001000100010011 ?
b10001000100010001000100010011 W
b10 <
b10 B
b10 G
b10 M
b10111 T
b11000 U
b11001 S
b111 :
b111 A
b111 D
b1100010111111110010110011 (
b1100010111111110010110011 +
b1100010111111110010110011 ,
b1100010111111110010110011 C
b100000 )
b100000 *
b100000 =
b100100 P
b100000 7
b100000 Q
b100000 R
b1000 #
1!
#130000
0!
#135000
b101100 .
b101100 >
b101100 L
b11111111111111111111111111110000 -
b11111111111111111111111111110000 O
b11111111111111111111111111110000 V
b101100 /
b101100 H
b101100 K
b101100 X
b11100 0
b11100 ?
b11100 W
b11111111111111111111111111110000 <
b11111111111111111111111111110000 B
b11111111111111111111111111110000 G
b11111111111111111111111111110000 M
b11011 T
b11100 U
b11101 S
b100000 9
b100000 @
b100000 E
b0 :
b0 A
b0 D
b1000001110011011000111010110011 (
b1000001110011011000111010110011 +
b1000001110011011000111010110011 ,
b1000001110011011000111010110011 C
b100100 )
b100100 *
b100100 =
b101000 P
b100100 7
b100100 Q
b100100 R
b1001 #
1!
#140000
0!
#145000
b111100 -
b111100 O
b111100 V
b11111111111111111111111111110000 .
b11111111111111111111111111110000 >
b11111111111111111111111111110000 L
b111100 <
b111100 B
b111100 G
b111100 M
b11111111111111111111111111110000 /
b11111111111111111111111111110000 H
b11111111111111111111111111110000 K
b11111111111111111111111111110000 X
b101100 0
b101100 ?
b101100 W
b11100 T
b11101 U
b11110 S
b1000001110111100000111100110011 (
b1000001110111100000111100110011 +
b1000001110111100000111100110011 ,
b1000001110111100000111100110011 C
b101000 )
b101000 *
b101000 =
b101100 P
b101000 7
b101000 Q
b101000 R
b1010 #
1!
#150000
0!
#155000
b1111 -
b1111 O
b1111 V
b1011 /
b1011 H
b1011 K
b1011 X
b1010 0
b1010 ?
b1010 W
b1111 <
b1111 B
b1111 G
b1111 M
b101 .
b101 >
b101 L
b100 T
b101 U
b110 S
b101 8
b101 F
b101 J
b0 9
b0 @
b0 E
1;
b10100100000001100010011 (
b10100100000001100010011 +
b10100100000001100010011 ,
b10100100000001100010011 C
b101100 )
b101100 *
b101100 =
b110000 P
b101100 7
b101100 Q
b101100 R
b1011 #
1!
#160000
0!
#165000
b11001 -
b11001 O
b11001 V
b11001 <
b11001 B
b11001 G
b11001 M
b1111000000000001000000 /
b1111000000000001000000 H
b1111000000000001000000 K
b1111000000000001000000 X
b1111 0
b1111 ?
b1111 W
b1010 .
b1010 >
b1010 L
b110 T
b1010 U
b111 S
b1010 8
b1010 F
b1010 J
b101000110000001110010011 (
b101000110000001110010011 +
b101000110000001110010011 ,
b101000110000001110010011 C
b110000 )
b110000 *
b110000 =
b110100 P
b110000 7
b110000 Q
b110000 R
b1100 #
1!
#170000
0!
#175000
b1 -
b1 O
b1 V
b1 /
b1 H
b1 K
b1 X
b11001 0
b11001 ?
b11001 W
b110010 .
b110010 >
b110010 L
b1 <
b1 B
b1 G
b1 M
b111 T
b10010 U
b1000 S
b110010 8
b110010 F
b110010 J
b1 9
b1 @
b1 E
b10 :
b10 A
b10 D
b11001000111010010000010011 (
b11001000111010010000010011 +
b11001000111010010000010011 ,
b11001000111010010000010011 C
b110100 )
b110100 *
b110100 =
b111000 P
b110100 7
b110100 Q
b110100 R
b1101 #
1!
#180000
0!
#185000
b0 -
b0 O
b0 V
b0 <
b0 B
b0 G
b0 M
b0 /
b0 H
b0 K
b0 X
b10100 .
b10100 >
b10100 L
b10100 U
b10100 8
b10100 F
b10100 J
b0 9
b0 @
b0 E
b1010000111010010000010011 (
b1010000111010010000010011 +
b1010000111010010000010011 ,
b1010000111010010000010011 C
b111000 )
b111000 *
b111000 =
b111100 P
b111000 7
b111000 Q
b111000 R
b1110 #
1!
#190000
0!
#195000
b11001 -
b11001 O
b11001 V
b0 .
b0 >
b0 L
b11001 <
b11001 B
b11001 G
b11001 M
b0 U
b0 8
b0 F
b0 J
b100 :
b100 A
b100 D
b111100010000010011 (
b111100010000010011 +
b111100010000010011 ,
b111100010000010011 C
b111100 )
b111100 *
b111100 =
b1000000 P
b111100 7
b111100 Q
b111100 R
b1111 #
1!
#200000
0!
#205000
b1001 S
b110 :
b110 A
b110 D
b111110010010010011 (
b111110010010010011 +
b111110010010010011 ,
b111110010010010011 C
b1000000 )
b1000000 *
b1000000 =
b1000100 P
b1000000 7
b1000000 Q
b1000000 R
b10000 #
1!
#210000
0!
#215000
b0 -
b0 O
b0 V
b0 <
b0 B
b0 G
b0 M
b1010 S
b111 :
b111 A
b111 D
b111111010100010011 (
b111111010100010011 +
b111111010100010011 ,
b111111010100010011 C
b1000100 )
b1000100 *
b1000100 =
b1001000 P
b1000100 7
b1000100 Q
b1000100 R
b10001 #
1!
#220000
0!
#225000
b110 /
b110 H
b110 K
b110 X
b0 0
b0 ?
b0 W
b1100 .
b1100 >
b1100 L
b10101011000001000101011000100000 -
b10101011000001000101011000100000 O
b10101011000001000101011000100000 V
15
b10101011000001000101011000100000 6
b10101011000001000101011000100000 I
b10101011000001000101011000100000 N
b1100 <
b1100 B
b1100 G
b1100 M
b1010 T
b1100 U
b1100 8
b1100 F
b1100 J
13
14
b0 :
b0 A
b0 D
b110001010010010100000011 (
b110001010010010100000011 +
b110001010010010100000011 ,
b110001010010010100000011 C
b1001000 )
b1001000 *
b1001000 =
b1001100 P
b1001000 7
b1001000 Q
b1001000 R
b10010 #
1!
#230000
0!
#235000
b101 /
b101 H
b101 K
b101 X
b0 T
b1110 U
b1100 S
x3
12
04
01
b1100 -
b1100 O
b1100 V
b111000000010011000100011 (
b111000000010011000100011 +
b111000000010011000100011 ,
b111000000010011000100011 C
bx 6
bx I
bx N
b1001100 )
b1001100 *
b1001100 =
b1100 <
b1100 B
b1100 G
b1100 M
b1010000 P
b1001100 7
b1001100 Q
b0 0
b0 ?
b0 W
b1001100 R
b10011 #
1!
#240000
0!
#245000
b10000 -
b10000 O
b10000 V
b10000 <
b10000 B
b10000 G
b10000 M
b10001000100010001000100010001 /
b10001000100010001000100010001 H
b10001000100010001000100010001 K
b10001000100010001000100010001 X
b10000 .
b10000 >
b10000 L
b10101 U
b10000 S
b10000 8
b10000 F
b10000 J
b1010100000010100000100011 (
b1010100000010100000100011 +
b1010100000010100000100011 ,
b1010100000010100000100011 C
b1010000 )
b1010000 *
b1010000 =
b1010100 P
b1010000 7
b1010000 Q
b1010000 R
b10100 #
1!
#250000
0!
#255000
b0 /
b0 H
b0 K
b0 X
b0 U
b0 S
b10 %
b100000 $
b10 &
b0 (
b0 +
b0 ,
b0 C
b1010100 )
b1010100 *
b1010100 =
b1011000 P
b1010100 7
b1010100 Q
b1010100 R
b10101 #
1!
